Workbook

Sheet ReadMe
A1: Generic Comet (GC) TIMES Residential
B3: Sheet color
C4: Parameters
C6: City Dashboard
C8: GC Databases
C10: TIMES formatted

Sheet >> City Data

Sheet City characteristics
B2: City Basic Data
B4: Calibration methodology | C4: GHG Inventory
B6: A. City Characteristics
B7: Data Item | C7: Value | D7: Units
B8: City Name | C8: New York
B9: Latitude | C9: 40.5
B10: Longitude | C10: -75
B11: County | C11: New York County
B12: State | C12: New York
B13: Census Division | C13: Middle Atlantic
B14: Climate Division | C14: Northeast
B15: Egrid Region | C15: NPCC NYC/Westchester
B16: Area of city (excluding water, natural and agricultural areas) | C16: 778 | D16: square kilometers
B17: * Division and Region Map can be found in the Maps sheet.
B18: B. Planning Base Year and Target Years
B19: Year | C19: Value | D19: Units
B20: Base Year | C20: 2019 | D20: Acceptable range [2018,2021]
B21: End Year | C21: 2050
B23: C. City Population and GDP
B24: Data Item | C24: Value | D24: Units
B25: Population in Base Year | C25: 8337 | D25: Thousand of people
B26: Annual population growth (Base Year - End Year) | C26: 0.5 | D26: % people
B27: GDP in Base Year | C27: 1206000 | D27: Million US$
B28: Annual GDP growth rate | C28: 2 | D28: % US$
B29: Share of manufacturing GDP | C29: 5 | D29: % US$
B30: Share of State population | C30: 0.42835123
B31: Share of State GDP | C31: 0.67251772
B32: Adjustment from state manufacturing GDP | C32: 1.0638298
B34: D. Climate Data
B35: Data Item | C35: 2000 | D35: 2050 | E35: 2100 | F35: Units
B36: Heating degree days (HDD) | C36: 4473.4625 | D36: 4066.4182 | E36: 3763.8582 | F36: F
B37: Cooling degree days (CDD) | C37: 1020.7333 | D37: 1224.2555 | E37: 1375.5355 | F37: F
B39: Data Item | C39: Value | D39: Units
B40: Correction from State HDD | C40: 0.72727402
B41: Correction from State CDD | C41: 1.5583715
B42: Annual precipitation | C42: 762 | D42: mm / year
B43: Climate change scenario | C43: RCP4.5
B44: Average temperature increase in 1980-2020 | C44: 1.4617857 | D44: F
B45: Forecasted average temperature increase in 2035-2065 | C45: 3.13 | D45: F
B46: Forecasted average temperature increase in 2070-2100 | C46: 4.37 | D46: F
B47: *Climate change scenario description can be found in the Lists sheet.
B48: E. Energy scenario
B49: Data Item | C49: Value | D49: Units
B50: AEO energy scenario | C50: lowmachighZTC
B51: Electricity technology scenario | C51: Moderate
B52: Transport technology scenario | C52: Mid
B53: District energy | C53: Yes
B54: * Energy scenario description can be foundin the Lists sheet.

Sheet >> GC_NewTech

Sheet RES TECH
A2: Sector | B2: Sub-sector | C2: Archetype | D2: Vintage | E2: End Use | F2: Technology | G2: Class | H2: Energy | I2: First Year | J2: Description | K2: Input Label | L2: Output Label | M2: Technology Label | N2: To include | O2: First availability year | P2: CAPEX (2023 US$ / unit) | Q2: Average size (MWs,PJa,Mlma / Thousands unit) | R2: Capacity Unit | S2: CAPEX (Thousands 2023 US$ / capacity) | T2: Efficiency | U2: Efficiency Unit | V2: Efficiency (%TJ) | W2: Min Lifetime | X2: Max Lifetime | Y2: Average Lifetime (year) | Z2: CFA | AA2: C2A
A3: Residential | B3: Apartment | C3: Low Income | D3: Old | E3: Water heating | G3: 1 | H3: Natural gas | I3: 2016 | J3: Water heating Class1 Natural gas 2016 | K3: RESNGA | L3: RESAPALOOldWHEUE | M3: RESAPALOOldWH1NGA20 | N3: 1 | O3: 2020 | P3: 2225.3303 | Q3: 1.8010645 | R3: MW | S3: 1235.5639 | T3: 0.61015 | U3: UEF | V3: 0.61015 | W3: 6 | X3: 20 | Y3: 14 | Z3: 0.24 | AA3: 31.536
A4: Residential | B4: Apartment | C4: Low Income | D4: Old | E4: Water heating | G4: 2 | H4: Natural gas | I4: 2016 | J4: Water heating Class2 Natural gas 2016 | K4: RESNGA | L4: RESAPALOOldWHEUE | M4: RESAPALOOldWH2NGA20 | N4: 1 | O4: 2020 | P4: 2347.2662 | Q4: 1.8010645 | R4: MW | S4: 1303.266 | T4: 0.63 | U4: UEF | V4: 0.63 | W4: 6 | X4: 20 | Y4: 14 | Z4: 0.24 | AA4: 31.536
A5: Residential | B5: Apartment | C5: Low Income | D5: Old | E5: Water heating | G5: 3 | H5: Natural gas | I5: 2016 | J5: Water heating Class3 Natural gas 2016 | K5: RESNGA | L5: RESAPALOOldWHEUE | M5: RESAPALOOldWH3NGA20 | N5: 1 | O5: 2020 | P5: 2469.2021 | Q5: 1.8010645 | R5: MW | S5: 1370.9682 | T5: 0.66 | U5: UEF | V5: 0.66 | W5: 6 | X5: 20 | Y5: 14 | Z5: 0.24 | AA5: 31.536
A6: Residential | B6: Apartment | C6: Low Income | D6: Old | E6: Water heating | G6: 3 | H6: Natural gas | I6: 2023 | J6: Water heating Class3 Natural gas 2023 | K6: RESNGA | L6: RESAPALOOldWHEUE | M6: RESAPALOOldWH3NGA23 | N6: 1 | O6: 2023 | P6: 3865.2554 | Q6: 1.8010645 | R6: MW | S6: 2146.0949 | T6: 0.835 | U6: UEF | V6: 0.835 | W6: 6 | X6: 20 | Y6: 14 | Z6: 0.24 | AA6: 31.536
A7: Residential | B7: Apartment | C7: Low Income | D7: Old | E7: Water heating | G7: 4 | H7: Natural gas | I7: 2016 | J7: Water heating Class4 Natural gas 2016 | K7: RESNGA | L7: RESAPALOOldWHEUE | M7: RESAPALOOldWH4NGA20 | N7: 0 | O7: 2020 | P7: 3749.5292 | Q7: 1.8010645 | R7: MW | S7: 2081.8406 | T7: 0.81 | U7: UEF | V7: 0.81 | W7: 6 | X7: 20 | Y7: 14 | Z7: 0.24 | AA7: 31.536
A8: Residential | B8: Apartment | C8: Low Income | D8: Old | E8: Water heating | G8: 4 | H8: Natural gas | I8: 2018 | J8: Water heating Class4 Natural gas 2018 | K8: RESNGA | L8: RESAPALOOldWHEUE | M8: RESAPALOOldWH4NGA20 | N8: 1 | O8: 2020 | P8: 3749.5292 | Q8: 1.8010645 | R8: MW | S8: 2081.8406 | T8: 0.81 | U8: UEF | V8: 0.81 | W8: 6 | X8: 20 | Y8: 14 | Z8: 0.24 | AA8: 31.536
A9: Residential | B9: Apartment | C9: Low Income | D9: Old | E9: Water heating | G9: 4 | H9: Natural gas | I9: 2022 | J9: Water heating Class4 Natural gas 2022 | K9: RESNGA | L9: RESAPALOOldWHEUE | M9: RESAPALOOldWH4NGA22 | N9: 1 | O9: 2022 | P9: 3749.5292 | Q9: 1.8010645 | R9: MW | S9: 2081.8406 | T9: 0.81 | U9: UEF | V9: 0.81 | W9: 6 | X9: 20 | Y9: 14 | Z9: 0.24 | AA9: 31.536
A10: Residential | B10: Apartment | C10: Low Income | D10: Old | E10: Water heating | G10: 1 | H10: Electricity | I10: 2016 | J10: Water heating Class1 Electricity 2016 | K10: RESELC | L10: RESAPALOOldWHEUE | M10: RESAPALOOldWH1ELC20 | N10: 1 | O10: 2020 | P10: 945.00328 | Q10: 1.8010645 | R10: MW | S10: 524.69152 | T10: 0.91555 | U10: UEF | V10: 0.91555 | W10: 6 | X10: 20 | Y10: 14 | Z10: 0.24 | AA10: 31.536
A11: Residential | B11: Apartment | C11: Low Income | D11: Old | E11: Water heating | G11: 2 | H11: Electricity | I11: 2016 | J11: Water heating Class2 Electricity 2016 | K11: RESELC | L11: RESAPALOOldWHEUE | M11: RESAPALOOldWH2ELC20 | N11: 1 | O11: 2020 | P11: 1036.4552 | Q11: 1.8010645 | R11: MW | S11: 575.46812 | T11: 0.93 | U11: UEF | V11: 0.93 | W11: 6 | X11: 20 | Y11: 14 | Z11: 0.24 | AA11: 31.536
A12: Residential | B12: Apartment | C12: Low Income | D12: Old | E12: Water heating | G12: 4 | H12: Electricity | I12: 2016 | J12: Water heating Class4 Electricity 2016 | K12: RESELC | L12: RESAPALOOldWHEUE | M12: RESAPALOOldWH4ELC20 | N12: 1 | O12: 2020 | P12: 1493.7149 | Q12: 1.8010645 | R12: MW | S12: 829.35112 | T12: 0.95 | U12: UEF | V12: 0.95 | W12: 6 | X12: 20 | Y12: 14 | Z12: 0.24 | AA12: 31.536
A13: Residential | B13: Apartment | C13: Low Income | D13: Old | E13: Water heating | G13: 5 | H13: Electricity | I13: 2016 | J13: Water heating Class5 Electricity 2016 | K13: RESELC | L13: RESAPALOOldWHEUE | M13: RESAPALOOldWH5ELC20 | N13: 1 | O13: 2020 | P13: 2530.1701 | Q13: 1.8010645 | R13: MW | S13: 1404.8192 | T13: 3.28 | U13: UEF | V13: 3.28 | W13: 6 | X13: 20 | Y13: 14 | Z13: 0.24 | AA13: 31.536
A14: Residential | B14: Apartment | C14: Low Income | D14: Old | E14: Water heating | G14: 5 | H14: Electricity | I14: 2022 | J14: Water heating Class5 Electricity 2022 | K14: RESELC | L14: RESAPALOOldWHEUE | M14: RESAPALOOldWH5ELC22 | N14: 1 | O14: 2022 | P14: 2530.1701 | Q14: 1.8010645 | R14: MW | S14: 1404.8192 | T14: 3.28 | U14: UEF | V14: 3.28 | W14: 6 | X14: 20 | Y14: 14 | Z14: 0.24 | AA14: 31.536
... A31: Residential | B31: Apartment | C31: Low Income | D31: Old | E31: Water heating | G31: 2 | H31: Solar | I31: 2024 | J31: Water heating Class2 Solar 2024 | K31: RESSOL | L31: RESAPALOOldWHEUE | M31: RESAPALOOldWH2SOL24 | N31: 1 | O31: 2024 | P31: 13412.95 | Q31: 1.8010645 | R31: MW | S31: 7447.2345 | T31: 1 | U31: SEF | V31: 1 | W31: 15 | X31: 30 | Y31: 23 | Z31: 0.24 | AA31: 31.536
A32: Residential | B32: Apartment | C32: Low Income | D32: Old | E32: Space heating | F32: Air HP | G32: 1 | H32: Electricity | I32: 2016 | J32: Space heating Air HP Class1 Electricity 2016 | K32: RESELC | L32: RESAPALOOldSHEUE | M32: RESAPALOOldSHAHP1ELC20 | N32: 1 | O32: 2020 | P32: 2956.9458 | Q32: 3.9515087 | R32: MW | S32: 748.30805 | T32: 2.4032825 | U32: COP | V32: 2.4032825 | W32: 9 | X32: 22 | Y32: 16 | Z32: 0.098628147 | AA32: 31.536
A33: Residential | B33: Apartment | C33: Low Income | D33: Old | E33: Space heating | F33: Air HP | G33: 1 | H33: Electricity | I33: 2023 | J33: Space heating Air HP Class1 Electricity 2023 | K33: RESELC | L33: RESAPALOOldSHEUE | M33: RESAPALOOldSHAHP1ELC23 | N33: 1 | O33: 2023 | P33: 2956.9458 | Q33: 3.9515087 | R33: MW | S33: 748.30805 | T33: 2.4032825 | U33: COP | V33: 2.4032825 | W33: 9 | X33: 22 | Y33: 16 | Z33: 0.098628147 | AA33: 31.536
A34: Residential | B34: Apartment | C34: Low Income | D34: Old | E34: Space heating | F34: Air HP | G34: 2 | H34: Electricity | I34: 2016 | J34: Space heating Air HP Class2 Electricity 2016 | K34: RESELC | L34: RESAPALOOldSHEUE | M34: RESAPALOOldSHAHP2ELC20 | N34: 1 | O34: 2020 | P34: 3109.3656 | Q34: 3.9515087 | R34: MW | S34: 786.88063 | T34: 2.5205158 | U34: COP | V34: 2.5205158 | W34: 9 | X34: 22 | Y34: 16 | Z34: 0.098628147 | AA34: 31.536
A35: Residential | B35: Apartment | C35: Low Income | D35: Old | E35: Space heating | F35: Air HP | G35: 2 | H35: Electricity | I35: 2023 | J35: Space heating Air HP Class2 Electricity 2023 | K35: RESELC | L35: RESAPALOOldSHEUE | M35: RESAPALOOldSHAHP2ELC23 | N35: 1 | O35: 2023 | P35: 3139.8496 | Q35: 3.9515087 | R35: MW | S35: 794.59514 | T35: 2.5791325 | U35: COP | V35: 2.5791325 | W35: 9 | X35: 22 | Y35: 16 | Z35: 0.098628147 | AA35: 31.536
A36: Residential | B36: Apartment | C36: Low Income | D36: Old | E36: Space heating | F36: Air HP | G36: 3 | H36: Electricity | I36: 2016 | J36: Space heating Air HP Class3 Electricity 2016 | K36: RESELC | L36: RESAPALOOldSHEUE | M36: RESAPALOOldSHAHP3ELC20 | N36: 1 | O36: 2020 | P36: 3017.9137 | Q36: 3.9515087 | R36: MW | S36: 763.73708 | T36: 2.4912075 | U36: COP | V36: 2.4912075 | W36: 9 | X36: 22 | Y36: 16 | Z36: 0.098628147 | AA36: 31.536
A37: Residential | B37: Apartment | C37: Low Income | D37: Old | E37: Space heating | F37: Air HP | G37: 3 | H37: Electricity | I37: 2022 | J37: Space heating Air HP Class3 Electricity 2022 | K37: RESELC | L37: RESAPALOOldSHEUE | M37: RESAPALOOldSHAHP3ELC22 | N37: 1 | O37: 2022 | P37: 3017.9137 | Q37: 3.9515087 | R37: MW | S37: 763.73708 | T37: 2.4912075 | U37: COP | V37: 2.4912075 | W37: 9 | X37: 22 | Y37: 16 | Z37: 0.098628147 | AA37: 31.536
A38: Residential | B38: Apartment | C38: Low Income | D38: Old | E38: Space heating | F38: Air HP | G38: 3 | H38: Electricity | I38: 2023 | J38: Space heating Air HP Class3 Electricity 2023 | K38: RESELC | L38: RESAPALOOldSHEUE | M38: RESAPALOOldSHAHP3ELC23 | N38: 1 | O38: 2023 | P38: 3266.4478 | Q38: 3.9515087 | R38: MW | S38: 826.63307 | T38: 2.6963658 | U38: COP | V38: 2.6963658 | W38: 9 | X38: 22 | Y38: 16 | Z38: 0.098628147 | AA38: 31.536
A39: Residential | B39: Apartment | C39: Low Income | D39: Old | E39: Space heating | F39: Air HP | G39: 4 | H39: Electricity | I39: 2016 | J39: Space heating Air HP Class4 Electricity 2016 | K39: RESELC | L39: RESAPALOOldSHEUE | M39: RESAPALOOldSHAHP4ELC20 | N39: 1 | O39: 2020 | P39: 3719.0452 | Q39: 3.9515087 | R39: MW | S39: 941.17095 | T39: 2.6377491 | U39: COP | V39: 2.6377491 | W39: 9 | X39: 22 | Y39: 16 | Z39: 0.098628147 | AA39: 31.536
A40: Residential | B40: Apartment | C40: Low Income | D40: Old | E40: Space heating | F40: Air HP | G40: 4 | H40: Electricity | I40: 2022 | J40: Space heating Air HP Class4 Electricity 2022 | K40: RESELC | L40: RESAPALOOldSHEUE | M40: RESAPALOOldSHAHP4ELC22 | N40: 1 | O40: 2022 | P40: 3914.7844 | Q40: 3.9515087 | R40: MW | S40: 990.70626 | T40: 2.9308324 | U40: COP | V40: 2.9308324 | W40: 9 | X40: 22 | Y40: 16 | Z40: 0.098628147 | AA40: 31.536
A41: Residential | B41: Apartment | C41: Low Income | D41: Old | E41: Space heating | F41: Geothermal HP | G41: 1 | H41: Electricity | I41: 2016 | J41: Space heating Geothermal HP Class1 Electricity 2016 | K41: RESELC | L41: RESAPALOOldSHEUE | M41: RESAPALOOldSHGHP1ELC20 | N41: 1 | O41: 2020 | P41: 9511.0008 | Q41: 3.9515087 | R41: MW | S41: 2406.929 | T41: 3.2 | U41: COP | V41: 3.2 | W41: 8 | X41: 20.8 | Y41: 15 | Z41: 0.098628147 | AA41: 31.536
A42: Residential | B42: Apartment | C42: Low Income | D42: Old | E42: Space heating | F42: Geothermal HP | G42: 2 | H42: Electricity | I42: 2016 | J42: Space heating Geothermal HP Class2 Electricity 2016 | K42: RESELC | L42: RESAPALOOldSHEUE | M42: RESAPALOOldSHGHP2ELC20 | N42: 1 | O42: 2020 | P42: 9846.3245 | Q42: 3.9515087 | R42: MW | S42: 2491.7886 | T42: 3.7 | U42: COP | V42: 3.7 | W42: 8 | X42: 20.8 | Y42: 15 | Z42: 0.098628147 | AA42: 31.536
A43: Residential | B43: Apartment | C43: Low Income | D43: Old | E43: Space heating | F43: Geothermal HP | G43: 3 | H43: Electricity | I43: 2016 | J43: Space heating Geothermal HP Class3 Electricity 2016 | K43: RESELC | L43: RESAPALOOldSHEUE | M43: RESAPALOOldSHGHP3ELC20 | N43: 0 | O43: 2020 | P43: 9846.3245 | Q43: 3.9515087 | R43: MW | S43: 2491.7886 | T43: 3.6 | U43: COP | V43: 3.6 | W43: 8 | X43: 20.8 | Y43: 15 | Z43: 0.098628147 | AA43: 31.536
... A132: Residential | B132: Apartment | C132: Low Income | D132: Old | E132: Space cooling | F132: Central AC | G132: 4 | H132: Electricity | I132: 2022 | J132: Space cooling Central AC Class4 Electricity 2022 | K132: RESELC | L132: RESAPALOOldSCEUE | M132: RESAPALOOldSCCAC4ELC22 | N132: 1 | O132: 2022 | P132: 5670.0197 | Q132: 1.7409371 | R132: MW | S132: 3256.878 | T132: 4.8358734 | U132: COP | V132: 4.8358734 | W132: 11 | X132: 25 | Y132: 19 | Z132: 0.082748623 | AA132: 31.536
A133: Residential | B133: Apartment | C133: Low Income | D133: Old | E133: Refrigeration | G133: TF1 | H133: Electricity | I133: 2016 | J133: Refrigeration ClassTF1 Electricity 2016 | K133: RESELC | L133: RESAPALOOldREEUE | M133: RESAPALOOldRETF1ELC20 | N133: 1 | O133: 2020 | P133: 853.55135 | Q133: 1.9035395 | R133: TJa | S133: 448.40222 | T133: 404.784 | U133: kWh/yr | V133: 1.1306816 | W133: 11.626 | X133: 21.895261 | Y133: 17 | Z133: 0.65 | AA133: 1
A134: Residential | B134: Apartment | C134: Low Income | D134: Old | E134: Refrigeration | G134: TF2 | H134: Electricity | I134: 2016 | J134: Refrigeration ClassTF2 Electricity 2016 | K134: RESELC | L134: RESAPALOOldREEUE | M134: RESAPALOOldRETF2ELC20 | N134: 1 | O134: 2020 | P134: 914.51931 | Q134: 1.9035395 | R134: TJa | S134: 480.43095 | T134: 389 | U134: kWh/yr | V134: 1.0865922 | W134: 11.626 | X134: 21.895261 | Y134: 17 | Z134: 0.65 | AA134: 1
A135: Residential | B135: Apartment | C135: Low Income | D135: Old | E135: Refrigeration | G135: TF3 | H135: Electricity | I135: 2016 | J135: Refrigeration ClassTF3 Electricity 2016 | K135: RESELC | L135: RESAPALOOldREEUE | M135: RESAPALOOldRETF3ELC20 | N135: 1 | O135: 2020 | P135: 1036.4552 | Q135: 1.9035395 | R135: TJa | S135: 544.48841 | T135: 364.3056 | U135: kWh/yr | V135: 1.0176134 | W135: 11.626 | X135: 21.895261 | Y135: 17 | Z135: 0.65 | AA135: 1
A136: Residential | B136: Apartment | C136: Low Income | D136: Old | E136: Refrigeration | G136: TF4 | H136: Electricity | I136: 2016 | J136: Refrigeration ClassTF4 Electricity 2016 | K136: RESELC | L136: RESAPALOOldREEUE | M136: RESAPALOOldRETF4ELC20 | N136: 1 | O136: 2020 | P136: 1073.036 | Q136: 1.9035395 | R136: TJa | S136: 563.70565 | T136: 358 | U136: kWh/yr | V136: 1 | W136: 11.626 | X136: 21.895261 | Y136: 17 | Z136: 0.65 | AA136: 1
A137: Residential | B137: Apartment | C137: Low Income | D137: Old | E137: Refrigeration | G137: SF1 | H137: Electricity | I137: 2016 | J137: Refrigeration ClassSF1 Electricity 2016 | K137: RESELC | L137: RESAPALOOldREEUE | M137: RESAPALOOldRESF1ELC20 | N137: 1 | O137: 2020 | P137: 1597.3604 | Q137: 1.9035395 | R137: TJa | S137: 839.15273 | T137: 705.226 | U137: kWh/yr | V137: 1.969905 | W137: 11.626 | X137: 21.895261 | Y137: 17 | Z137: 0.65 | AA137: 1
A138: Residential | B138: Apartment | C138: Low Income | D138: Old | E138: Refrigeration | G138: SF2 | H138: Electricity | I138: 2016 | J138: Refrigeration ClassSF2 Electricity 2016 | K138: RESELC | L138: RESAPALOOldREEUE | M138: RESAPALOOldRESF2ELC20 | N138: 1 | O138: 2020 | P138: 1731.4899 | Q138: 1.9035395 | R138: TJa | S138: 909.61594 | T138: 671 | U138: kWh/yr | V138: 1.8743017 | W138: 11.626 | X138: 21.895261 | Y138: 17 | Z138: 0.65 | AA138: 1
A139: Residential | B139: Apartment | C139: Low Income | D139: Old | E139: Refrigeration | G139: SF3 | H139: Electricity | I139: 2016 | J139: Refrigeration ClassSF3 Electricity 2016 | K139: RESELC | L139: RESAPALOOldREEUE | M139: RESAPALOOldRESF3ELC20 | N139: 1 | O139: 2020 | P139: 1890.0066 | Q139: 1.9035395 | R139: TJa | S139: 992.89064 | T139: 634.7034 | U139: kWh/yr | V139: 1.7729145 | W139: 11.626 | X139: 21.895261 | Y139: 17 | Z139: 0.65 | AA139: 1
A140: Residential | B140: Apartment | C140: Low Income | D140: Old | E140: Refrigeration | G140: SF4 | H140: Electricity | I140: 2016 | J140: Refrigeration ClassSF4 Electricity 2016 | K140: RESELC | L140: RESAPALOOldREEUE | M140: RESAPALOOldRESF4ELC20 | N140: 1 | O140: 2020 | P140: 2414.331 | Q140: 1.9035395 | R140: TJa | S140: 1268.3377 | T140: 509 | U140: kWh/yr | V140: 1.4217877 | W140: 11.626 | X140: 21.895261 | Y140: 17 | Z140: 0.65 | AA140: 1
A141: Residential | B141: Apartment | C141: Low Income | D141: Old | E141: Refrigeration | G141: BF1 | H141: Electricity | I141: 2016 | J141: Refrigeration ClassBF1 Electricity 2016 | K141: RESELC | L141: RESAPALOOldREEUE | M141: RESAPALOOldREBF1ELC20 | N141: 1 | O141: 2020 | P141: 1255.9398 | Q141: 1.9035395 | R141: TJa | S141: 659.79184 | T141: 520.55 | U141: kWh/yr | V141: 1.4540503 | W141: 11.626 | X141: 21.895261 | Y141: 17 | Z141: 0.65 | AA141: 1
A142: Residential | B142: Apartment | C142: Low Income | D142: Old | E142: Refrigeration | G142: BF2 | H142: Electricity | I142: 2016 | J142: Refrigeration ClassBF2 Electricity 2016 | K142: RESELC | L142: RESAPALOOldREEUE | M142: RESAPALOOldREBF2ELC20 | N142: 1 | O142: 2020 | P142: 1365.6822 | Q142: 1.9035395 | R142: TJa | S142: 717.44356 | T142: 480 | U142: kWh/yr | V142: 1.3407821 | W142: 11.626 | X142: 21.895261 | Y142: 17 | Z142: 0.65 | AA142: 1
A143: Residential | B143: Apartment | C143: Low Income | D143: Old | E143: Refrigeration | G143: BF3 | H143: Electricity | I143: 2016 | J143: Refrigeration ClassBF3 Electricity 2016 | K143: RESELC | L143: RESAPALOOldREEUE | M143: RESAPALOOldREBF3ELC20 | N143: 1 | O143: 2020 | P143: 1414.4565 | Q143: 1.9035395 | R143: TJa | S143: 743.06654 | T143: 469 | U143: kWh/yr | V143: 1.3100559 | W143: 11.626 | X143: 21.895261 | Y143: 17 | Z143: 0.65 | AA143: 1
A144: Residential | B144: Apartment | C144: Low Income | D144: Old | E144: Refrigeration | G144: BF4 | H144: Electricity | I144: 2016 | J144: Refrigeration ClassBF4 Electricity 2016 | K144: RESELC | L144: RESAPALOOldREEUE | M144: RESAPALOOldREBF4ELC20 | N144: 1 | O144: 2020 | P144: 1414.4565 | Q144: 1.9035395 | R144: TJa | S144: 743.06654 | T144: 469 | U144: kWh/yr | V144: 1.3100559 | W144: 11.626 | X144: 21.895261 | Y144: 17 | Z144: 0.65 | AA144: 1
... A207: Residential | B207: House | C207: Low Income | D207: Old | E207: Water heating | G207: 2 | H207: Solar | I207: 2024 | J207: Water heating Class2 Solar 2024 | K207: RESSOL | L207: RESHOULOOldWHEUE | M207: RESHOULOOldWH2SOL24 | N207: 1 | O207: 2024 | P207: 13412.95 | Q207: 1.7376707 | R207: MW | S207: 7718.9249 | T207: 1 | U207: SEF | V207: 1 | W207: 15 | X207: 30 | Y207: 23 | Z207: 0.24 | AA207: 31.536
A208: Residential | B208: House | C208: Low Income | D208: Old | E208: Space heating | F208: Air HP | G208: 1 | H208: Electricity | I208: 2016 | J208: Space heating Air HP Class1 Electricity 2016 | K208: RESELC | L208: RESHOULOOldSHEUE | M208: RESHOULOOldSHAHP1ELC20 | N208: 1 | O208: 2020 | P208: 2956.9458 | Q208: 15.047429 | R208: MW | S208: 196.50837 | T208: 2.4032825 | U208: COP | V208: 2.4032825 | W208: 9 | X208: 22 | Y208: 16 | Z208: 0.090305172 | AA208: 31.536
A209: Residential | B209: House | C209: Low Income | D209: Old | E209: Space heating | F209: Air HP | G209: 1 | H209: Electricity | I209: 2023 | J209: Space heating Air HP Class1 Electricity 2023 | K209: RESELC | L209: RESHOULOOldSHEUE | M209: RESHOULOOldSHAHP1ELC23 | N209: 1 | O209: 2023 | P209: 2956.9458 | Q209: 15.047429 | R209: MW | S209: 196.50837 | T209: 2.4032825 | U209: COP | V209: 2.4032825 | W209: 9 | X209: 22 | Y209: 16 | Z209: 0.090305172 | AA209: 31.536
A210: Residential | B210: House | C210: Low Income | D210: Old | E210: Space heating | F210: Air HP | G210: 2 | H210: Electricity | I210: 2016 | J210: Space heating Air HP Class2 Electricity 2016 | K210: RESELC | L210: RESHOULOOldSHEUE | M210: RESHOULOOldSHAHP2ELC20 | N210: 1 | O210: 2020 | P210: 3109.3656 | Q210: 15.047429 | R210: MW | S210: 206.63767 | T210: 2.5205158 | U210: COP | V210: 2.5205158 | W210: 9 | X210: 22 | Y210: 16 | Z210: 0.090305172 | AA210: 31.536
A211: Residential | B211: House | C211: Low Income | D211: Old | E211: Space heating | F211: Air HP | G211: 2 | H211: Electricity | I211: 2023 | J211: Space heating Air HP Class2 Electricity 2023 | K211: RESELC | L211: RESHOULOOldSHEUE | M211: RESHOULOOldSHAHP2ELC23 | N211: 1 | O211: 2023 | P211: 3139.8496 | Q211: 15.047429 | R211: MW | S211: 208.66353 | T211: 2.5791325 | U211: COP | V211: 2.5791325 | W211: 9 | X211: 22 | Y211: 16 | Z211: 0.090305172 | AA211: 31.536
A212: Residential | B212: House | C212: Low Income | D212: Old | E212: Space heating | F212: Air HP | G212: 3 | H212: Electricity | I212: 2016 | J212: Space heating Air HP Class3 Electricity 2016 | K212: RESELC | L212: RESHOULOOldSHEUE | M212: RESHOULOOldSHAHP3ELC20 | N212: 1 | O212: 2020 | P212: 3017.9137 | Q212: 15.047429 | R212: MW | S212: 200.56009 | T212: 2.4912075 | U212: COP | V212: 2.4912075 | W212: 9 | X212: 22 | Y212: 16 | Z212: 0.090305172 | AA212: 31.536
A213: Residential | B213: House | C213: Low Income | D213: Old | E213: Space heating | F213: Air HP | G213: 3 | H213: Electricity | I213: 2022 | J213: Space heating Air HP Class3 Electricity 2022 | K213: RESELC | L213: RESHOULOOldSHEUE | M213: RESHOULOOldSHAHP3ELC22 | N213: 1 | O213: 2022 | P213: 3017.9137 | Q213: 15.047429 | R213: MW | S213: 200.56009 | T213: 2.4912075 | U213: COP | V213: 2.4912075 | W213: 9 | X213: 22 | Y213: 16 | Z213: 0.090305172 | AA213: 31.536
A214: Residential | B214: House | C214: Low Income | D214: Old | E214: Space heating | F214: Air HP | G214: 3 | H214: Electricity | I214: 2023 | J214: Space heating Air HP Class3 Electricity 2023 | K214: RESELC | L214: RESHOULOOldSHEUE | M214: RESHOULOOldSHAHP3ELC23 | N214: 1 | O214: 2023 | P214: 3266.4478 | Q214: 15.047429 | R214: MW | S214: 217.07681 | T214: 2.6963658 | U214: COP | V214: 2.6963658 | W214: 9 | X214: 22 | Y214: 16 | Z214: 0.090305172 | AA214: 31.536
A215: Residential | B215: House | C215: Low Income | D215: Old | E215: Space heating | F215: Air HP | G215: 4 | H215: Electricity | I215: 2016 | J215: Space heating Air HP Class4 Electricity 2016 | K215: RESELC | L215: RESHOULOOldSHEUE | M215: RESHOULOOldSHAHP4ELC20 | N215: 1 | O215: 2020 | P215: 3719.0452 | Q215: 15.047429 | R215: MW | S215: 247.15486 | T215: 2.6377491 | U215: COP | V215: 2.6377491 | W215: 9 | X215: 22 | Y215: 16 | Z215: 0.090305172 | AA215: 31.536
A216: Residential | B216: House | C216: Low Income | D216: Old | E216: Space heating | F216: Air HP | G216: 4 | H216: Electricity | I216: 2022 | J216: Space heating Air HP Class4 Electricity 2022 | K216: RESELC | L216: RESHOULOOldSHEUE | M216: RESHOULOOldSHAHP4ELC22 | N216: 1 | O216: 2022 | P216: 3914.7844 | Q216: 15.047429 | R216: MW | S216: 260.16301 | T216: 2.9308324 | U216: COP | V216: 2.9308324 | W216: 9 | X216: 22 | Y216: 16 | Z216: 0.090305172 | AA216: 31.536
A217: Residential | B217: House | C217: Low Income | D217: Old | E217: Space heating | F217: Geothermal HP | G217: 1 | H217: Electricity | I217: 2016 | J217: Space heating Geothermal HP Class1 Electricity 2016 | K217: RESELC | L217: RESHOULOOldSHEUE | M217: RESHOULOOldSHGHP1ELC20 | N217: 1 | O217: 2020 | P217: 9511.0008 | Q217: 15.047429 | R217: MW | S217: 632.06817 | T217: 3.2 | U217: COP | V217: 3.2 | W217: 8 | X217: 20.8 | Y217: 15 | Z217: 0.090305172 | AA217: 31.536
A218: Residential | B218: House | C218: Low Income | D218: Old | E218: Space heating | F218: Geothermal HP | G218: 2 | H218: Electricity | I218: 2016 | J218: Space heating Geothermal HP Class2 Electricity 2016 | K218: RESELC | L218: RESHOULOOldSHEUE | M218: RESHOULOOldSHGHP2ELC20 | N218: 1 | O218: 2020 | P218: 9846.3245 | Q218: 15.047429 | R218: MW | S218: 654.35263 | T218: 3.7 | U218: COP | V218: 3.7 | W218: 8 | X218: 20.8 | Y218: 15 | Z218: 0.090305172 | AA218: 31.536
A219: Residential | B219: House | C219: Low Income | D219: Old | E219: Space heating | F219: Geothermal HP | G219: 3 | H219: Electricity | I219: 2016 | J219: Space heating Geothermal HP Class3 Electricity 2016 | K219: RESELC | L219: RESHOULOOldSHEUE | M219: RESHOULOOldSHGHP3ELC20 | N219: 0 | O219: 2020 | P219: 9846.3245 | Q219: 15.047429 | R219: MW | S219: 654.35263 | T219: 3.6 | U219: COP | V219: 3.6 | W219: 8 | X219: 20.8 | Y219: 15 | Z219: 0.090305172 | AA219: 31.536
... A308: Residential | B308: House | C308: Low Income | D308: Old | E308: Space cooling | F308: Central AC | G308: 4 | H308: Electricity | I308: 2022 | J308: Space cooling Central AC Class4 Electricity 2022 | K308: RESELC | L308: RESHOULOOldSCEUE | M308: RESHOULOOldSCCAC4ELC22 | N308: 1 | O308: 2022 | P308: 5670.0197 | Q308: 3.6463117 | R308: MW | S308: 1555.0014 | T308: 4.8358734 | U308: COP | V308: 4.8358734 | W308: 11 | X308: 25 | Y308: 19 | Z308: 0.080981186 | AA308: 31.536
A309: Residential | B309: House | C309: Low Income | D309: Old | E309: Refrigeration | G309: TF1 | H309: Electricity | I309: 2016 | J309: Refrigeration ClassTF1 Electricity 2016 | K309: RESELC | L309: RESHOULOOldREEUE | M309: RESHOULOOldRETF1ELC20 | N309: 1 | O309: 2020 | P309: 853.55135 | Q309: 3.3741105 | R309: TJa | S309: 252.97078 | T309: 404.784 | U309: kWh/yr | V309: 1.1306816 | W309: 11.626 | X309: 21.895261 | Y309: 17 | Z309: 0.65 | AA309: 1
A310: Residential | B310: House | C310: Low Income | D310: Old | E310: Refrigeration | G310: TF2 | H310: Electricity | I310: 2016 | J310: Refrigeration ClassTF2 Electricity 2016 | K310: RESELC | L310: RESHOULOOldREEUE | M310: RESHOULOOldRETF2ELC20 | N310: 1 | O310: 2020 | P310: 914.51931 | Q310: 3.3741105 | R310: TJa | S310: 271.04012 | T310: 389 | U310: kWh/yr | V310: 1.0865922 | W310: 11.626 | X310: 21.895261 | Y310: 17 | Z310: 0.65 | AA310: 1
A311: Residential | B311: House | C311: Low Income | D311: Old | E311: Refrigeration | G311: TF3 | H311: Electricity | I311: 2016 | J311: Refrigeration ClassTF3 Electricity 2016 | K311: RESELC | L311: RESHOULOOldREEUE | M311: RESHOULOOldRETF3ELC20 | N311: 1 | O311: 2020 | P311: 1036.4552 | Q311: 3.3741105 | R311: TJa | S311: 307.1788 | T311: 364.3056 | U311: kWh/yr | V311: 1.0176134 | W311: 11.626 | X311: 21.895261 | Y311: 17 | Z311: 0.65 | AA311: 1
A312: Residential | B312: House | C312: Low Income | D312: Old | E312: Refrigeration | G312: TF4 | H312: Electricity | I312: 2016 | J312: Refrigeration ClassTF4 Electricity 2016 | K312: RESELC | L312: RESHOULOOldREEUE | M312: RESHOULOOldRETF4ELC20 | N312: 1 | O312: 2020 | P312: 1073.036 | Q312: 3.3741105 | R312: TJa | S312: 318.02041 | T312: 358 | U312: kWh/yr | V312: 1 | W312: 11.626 | X312: 21.895261 | Y312: 17 | Z312: 0.65 | AA312: 1
A313: Residential | B313: House | C313: Low Income | D313: Old | E313: Refrigeration | G313: SF1 | H313: Electricity | I313: 2016 | J313: Refrigeration ClassSF1 Electricity 2016 | K313: RESELC | L313: RESHOULOOldREEUE | M313: RESHOULOOldRESF1ELC20 | N313: 1 | O313: 2020 | P313: 1597.3604 | Q313: 3.3741105 | R313: TJa | S313: 473.41674 | T313: 705.226 | U313: kWh/yr | V313: 1.969905 | W313: 11.626 | X313: 21.895261 | Y313: 17 | Z313: 0.65 | AA313: 1
A314: Residential | B314: House | C314: Low Income | D314: Old | E314: Refrigeration | G314: SF2 | H314: Electricity | I314: 2016 | J314: Refrigeration ClassSF2 Electricity 2016 | K314: RESELC | L314: RESHOULOOldREEUE | M314: RESHOULOOldRESF2ELC20 | N314: 1 | O314: 2020 | P314: 1731.4899 | Q314: 3.3741105 | R314: TJa | S314: 513.16929 | T314: 671 | U314: kWh/yr | V314: 1.8743017 | W314: 11.626 | X314: 21.895261 | Y314: 17 | Z314: 0.65 | AA314: 1
A315: Residential | B315: House | C315: Low Income | D315: Old | E315: Refrigeration | G315: SF3 | H315: Electricity | I315: 2016 | J315: Refrigeration ClassSF3 Electricity 2016 | K315: RESELC | L315: RESHOULOOldREEUE | M315: RESHOULOOldRESF3ELC20 | N315: 1 | O315: 2020 | P315: 1890.0066 | Q315: 3.3741105 | R315: TJa | S315: 560.14958 | T315: 634.7034 | U315: kWh/yr | V315: 1.7729145 | W315: 11.626 | X315: 21.895261 | Y315: 17 | Z315: 0.65 | AA315: 1
A316: Residential | B316: House | C316: Low Income | D316: Old | E316: Refrigeration | G316: SF4 | H316: Electricity | I316: 2016 | J316: Refrigeration ClassSF4 Electricity 2016 | K316: RESELC | L316: RESHOULOOldREEUE | M316: RESHOULOOldRESF4ELC20 | N316: 1 | O316: 2020 | P316: 2414.331 | Q316: 3.3741105 | R316: TJa | S316: 715.54591 | T316: 509 | U316: kWh/yr | V316: 1.4217877 | W316: 11.626 | X316: 21.895261 | Y316: 17 | Z316: 0.65 | AA316: 1
A317: Residential | B317: House | C317: Low Income | D317: Old | E317: Refrigeration | G317: BF1 | H317: Electricity | I317: 2016 | J317: Refrigeration ClassBF1 Electricity 2016 | K317: RESELC | L317: RESHOULOOldREEUE | M317: RESHOULOOldREBF1ELC20 | N317: 1 | O317: 2020 | P317: 1255.9398 | Q317: 3.3741105 | R317: TJa | S317: 372.22843 | T317: 520.55 | U317: kWh/yr | V317: 1.4540503 | W317: 11.626 | X317: 21.895261 | Y317: 17 | Z317: 0.65 | AA317: 1
A318: Residential | B318: House | C318: Low Income | D318: Old | E318: Refrigeration | G318: BF2 | H318: Electricity | I318: 2016 | J318: Refrigeration ClassBF2 Electricity 2016 | K318: RESELC | L318: RESHOULOOldREEUE | M318: RESHOULOOldREBF2ELC20 | N318: 1 | O318: 2020 | P318: 1365.6822 | Q318: 3.3741105 | R318: TJa | S318: 404.75324 | T318: 480 | U318: kWh/yr | V318: 1.3407821 | W318: 11.626 | X318: 21.895261 | Y318: 17 | Z318: 0.65 | AA318: 1
A319: Residential | B319: House | C319: Low Income | D319: Old | E319: Refrigeration | G319: BF3 | H319: Electricity | I319: 2016 | J319: Refrigeration ClassBF3 Electricity 2016 | K319: RESELC | L319: RESHOULOOldREEUE | M319: RESHOULOOldREBF3ELC20 | N319: 1 | O319: 2020 | P319: 1414.4565 | Q319: 3.3741105 | R319: TJa | S319: 419.20872 | T319: 469 | U319: kWh/yr | V319: 1.3100559 | W319: 11.626 | X319: 21.895261 | Y319: 17 | Z319: 0.65 | AA319: 1
A320: Residential | B320: House | C320: Low Income | D320: Old | E320: Refrigeration | G320: BF4 | H320: Electricity | I320: 2016 | J320: Refrigeration ClassBF4 Electricity 2016 | K320: RESELC | L320: RESHOULOOldREEUE | M320: RESHOULOOldREBF4ELC20 | N320: 1 | O320: 2020 | P320: 1414.4565 | Q320: 3.3741105 | R320: TJa | S320: 419.20872 | T320: 469 | U320: kWh/yr | V320: 1.3100559 | W320: 11.626 | X320: 21.895261 | Y320: 17 | Z320: 0.65 | AA320: 1
... A383: Residential | B383: Apartment | C383: Lower-middle Income | D383: Old | E383: Water heating | G383: 2 | H383: Solar | I383: 2024 | J383: Water heating Class2 Solar 2024 | K383: RESSOL | L383: RESAPALMOldWHEUE | M383: RESAPALMOldWH2SOL24 | N383: 1 | O383: 2024 | P383: 13412.95 | Q383: 1.5324032 | R383: MW | S383: 8752.8856 | T383: 1 | U383: SEF | V383: 1 | W383: 15 | X383: 30 | Y383: 23 | Z383: 0.24 | AA383: 31.536
A384: Residential | B384: Apartment | C384: Lower-middle Income | D384: Old | E384: Space heating | F384: Air HP | G384: 1 | H384: Electricity | I384: 2016 | J384: Space heating Air HP Class1 Electricity 2016 | K384: RESELC | L384: RESAPALMOldSHEUE | M384: RESAPALMOldSHAHP1ELC20 | N384: 1 | O384: 2020 | P384: 2956.9458 | Q384: 4.380808 | R384: MW | S384: 674.97726 | T384: 2.4032825 | U384: COP | V384: 2.4032825 | W384: 9 | X384: 22 | Y384: 16 | Z384: 0.090799343 | AA384: 31.536
A385: Residential | B385: Apartment | C385: Lower-middle Income | D385: Old | E385: Space heating | F385: Air HP | G385: 1 | H385: Electricity | I385: 2023 | J385: Space heating Air HP Class1 Electricity 2023 | K385: RESELC | L385: RESAPALMOldSHEUE | M385: RESAPALMOldSHAHP1ELC23 | N385: 1 | O385: 2023 | P385: 2956.9458 | Q385: 4.380808 | R385: MW | S385: 674.97726 | T385: 2.4032825 | U385: COP | V385: 2.4032825 | W385: 9 | X385: 22 | Y385: 16 | Z385: 0.090799343 | AA385: 31.536
A386: Residential | B386: Apartment | C386: Lower-middle Income | D386: Old | E386: Space heating | F386: Air HP | G386: 2 | H386: Electricity | I386: 2016 | J386: Space heating Air HP Class2 Electricity 2016 | K386: RESELC | L386: RESAPALMOldSHEUE | M386: RESAPALMOldSHAHP2ELC20 | N386: 1 | O386: 2020 | P386: 3109.3656 | Q386: 4.380808 | R386: MW | S386: 709.7699 | T386: 2.5205158 | U386: COP | V386: 2.5205158 | W386: 9 | X386: 22 | Y386: 16 | Z386: 0.090799343 | AA386: 31.536
A387: Residential | B387: Apartment | C387: Lower-middle Income | D387: Old | E387: Space heating | F387: Air HP | G387: 2 | H387: Electricity | I387: 2023 | J387: Space heating Air HP Class2 Electricity 2023 | K387: RESELC | L387: RESAPALMOldSHEUE | M387: RESAPALMOldSHAHP2ELC23 | N387: 1 | O387: 2023 | P387: 3139.8496 | Q387: 4.380808 | R387: MW | S387: 716.72843 | T387: 2.5791325 | U387: COP | V387: 2.5791325 | W387: 9 | X387: 22 | Y387: 16 | Z387: 0.090799343 | AA387: 31.536
A388: Residential | B388: Apartment | C388: Lower-middle Income | D388: Old | E388: Space heating | F388: Air HP | G388: 3 | H388: Electricity | I388: 2016 | J388: Space heating Air HP Class3 Electricity 2016 | K388: RESELC | L388: RESAPALMOldSHEUE | M388: RESAPALMOldSHAHP3ELC20 | N388: 1 | O388: 2020 | P388: 3017.9137 | Q388: 4.380808 | R388: MW | S388: 688.89432 | T388: 2.4912075 | U388: COP | V388: 2.4912075 | W388: 9 | X388: 22 | Y388: 16 | Z388: 0.090799343 | AA388: 31.536
A389: Residential | B389: Apartment | C389: Lower-middle Income | D389: Old | E389: Space heating | F389: Air HP | G389: 3 | H389: Electricity | I389: 2022 | J389: Space heating Air HP Class3 Electricity 2022 | K389: RESELC | L389: RESAPALMOldSHEUE | M389: RESAPALMOldSHAHP3ELC22 | N389: 1 | O389: 2022 | P389: 3017.9137 | Q389: 4.380808 | R389: MW | S389: 688.89432 | T389: 2.4912075 | U389: COP | V389: 2.4912075 | W389: 9 | X389: 22 | Y389: 16 | Z389: 0.090799343 | AA389: 31.536
A390: Residential | B390: Apartment | C390: Lower-middle Income | D390: Old | E390: Space heating | F390: Air HP | G390: 3 | H390: Electricity | I390: 2023 | J390: Space heating Air HP Class3 Electricity 2023 | K390: RESELC | L390: RESAPALMOldSHEUE | M390: RESAPALMOldSHAHP3ELC23 | N390: 1 | O390: 2023 | P390: 3266.4478 | Q390: 4.380808 | R390: MW | S390: 745.62679 | T390: 2.6963658 | U390: COP | V390: 2.6963658 | W390: 9 | X390: 22 | Y390: 16 | Z390: 0.090799343 | AA390: 31.536
A391: Residential | B391: Apartment | C391: Lower-middle Income | D391: Old | E391: Space heating | F391: Air HP | G391: 4 | H391: Electricity | I391: 2016 | J391: Space heating Air HP Class4 Electricity 2016 | K391: RESELC | L391: RESAPALMOldSHEUE | M391: RESAPALMOldSHAHP4ELC20 | N391: 1 | O391: 2020 | P391: 3719.0452 | Q391: 4.380808 | R391: MW | S391: 848.94047 | T391: 2.6377491 | U391: COP | V391: 2.6377491 | W391: 9 | X391: 22 | Y391: 16 | Z391: 0.090799343 | AA391: 31.536
A392: Residential | B392: Apartment | C392: Lower-middle Income | D392: Old | E392: Space heating | F392: Air HP | G392: 4 | H392: Electricity | I392: 2022 | J392: Space heating Air HP Class4 Electricity 2022 | K392: RESELC | L392: RESAPALMOldSHEUE | M392: RESAPALMOldSHAHP4ELC22 | N392: 1 | O392: 2022 | P392: 3914.7844 | Q392: 4.380808 | R392: MW | S392: 893.62155 | T392: 2.9308324 | U392: COP | V392: 2.9308324 | W392: 9 | X392: 22 | Y392: 16 | Z392: 0.090799343 | AA392: 31.536
A393: Residential | B393: Apartment | C393: Lower-middle Income | D393: Old | E393: Space heating | F393: Geothermal HP | G393: 1 | H393: Electricity | I393: 2016 | J393: Space heating Geothermal HP Class1 Electricity 2016 | K393: RESELC | L393: RESAPALMOldSHEUE | M393: RESAPALMOldSHGHP1ELC20 | N393: 1 | O393: 2020 | P393: 9511.0008 | Q393: 4.380808 | R393: MW | S393: 2171.0609 | T393: 3.2 | U393: COP | V393: 3.2 | W393: 8 | X393: 20.8 | Y393: 15 | Z393: 0.090799343 | AA393: 31.536
A394: Residential | B394: Apartment | C394: Lower-middle Income | D394: Old | E394: Space heating | F394: Geothermal HP | G394: 2 | H394: Electricity | I394: 2016 | J394: Space heating Geothermal HP Class2 Electricity 2016 | K394: RESELC | L394: RESAPALMOldSHEUE | M394: RESAPALMOldSHGHP2ELC20 | N394: 1 | O394: 2020 | P394: 9846.3245 | Q394: 4.380808 | R394: MW | S394: 2247.6047 | T394: 3.7 | U394: COP | V394: 3.7 | W394: 8 | X394: 20.8 | Y394: 15 | Z394: 0.090799343 | AA394: 31.536
A395: Residential | B395: Apartment | C395: Lower-middle Income | D395: Old | E395: Space heating | F395: Geothermal HP | G395: 3 | H395: Electricity | I395: 2016 | J395: Space heating Geothermal HP Class3 Electricity 2016 | K395: RESELC | L395: RESAPALMOldSHEUE | M395: RESAPALMOldSHGHP3ELC20 | N395: 0 | O395: 2020 | P395: 9846.3245 | Q395: 4.380808 | R395: MW | S395: 2247.6047 | T395: 3.6 | U395: COP | V395: 3.6 | W395: 8 | X395: 20.8 | Y395: 15 | Z395: 0.090799343 | AA395: 31.536
... A484: Residential | B484: Apartment | C484: Lower-middle Income | D484: Old | E484: Space cooling | F484: Central AC | G484: 4 | H484: Electricity | I484: 2022 | J484: Space cooling Central AC Class4 Electricity 2022 | K484: RESELC | L484: RESAPALMOldSCEUE | M484: RESAPALMOldSCCAC4ELC22 | N484: 1 | O484: 2022 | P484: 5670.0197 | Q484: 2.0610138 | R484: MW | S484: 2751.0829 | T484: 4.8358734 | U484: COP | V484: 4.8358734 | W484: 11 | X484: 25 | Y484: 19 | Z484: 0.079838655 | AA484: 31.536
A485: Residential | B485: Apartment | C485: Lower-middle Income | D485: Old | E485: Refrigeration | G485: TF1 | H485: Electricity | I485: 2016 | J485: Refrigeration ClassTF1 Electricity 2016 | K485: RESELC | L485: RESAPALMOldREEUE | M485: RESAPALMOldRETF1ELC20 | N485: 1 | O485: 2020 | P485: 853.55135 | Q485: 1.892911 | R485: TJa | S485: 450.91996 | T485: 404.784 | U485: kWh/yr | V485: 1.1306816 | W485: 11.626 | X485: 21.895261 | Y485: 17 | Z485: 0.65 | AA485: 1
A486: Residential | B486: Apartment | C486: Lower-middle Income | D486: Old | E486: Refrigeration | G486: TF2 | H486: Electricity | I486: 2016 | J486: Refrigeration ClassTF2 Electricity 2016 | K486: RESELC | L486: RESAPALMOldREEUE | M486: RESAPALMOldRETF2ELC20 | N486: 1 | O486: 2020 | P486: 914.51931 | Q486: 1.892911 | R486: TJa | S486: 483.12853 | T486: 389 | U486: kWh/yr | V486: 1.0865922 | W486: 11.626 | X486: 21.895261 | Y486: 17 | Z486: 0.65 | AA486: 1
A487: Residential | B487: Apartment | C487: Lower-middle Income | D487: Old | E487: Refrigeration | G487: TF3 | H487: Electricity | I487: 2016 | J487: Refrigeration ClassTF3 Electricity 2016 | K487: RESELC | L487: RESAPALMOldREEUE | M487: RESAPALMOldRETF3ELC20 | N487: 1 | O487: 2020 | P487: 1036.4552 | Q487: 1.892911 | R487: TJa | S487: 547.54566 | T487: 364.3056 | U487: kWh/yr | V487: 1.0176134 | W487: 11.626 | X487: 21.895261 | Y487: 17 | Z487: 0.65 | AA487: 1
A488: Residential | B488: Apartment | C488: Lower-middle Income | D488: Old | E488: Refrigeration | G488: TF4 | H488: Electricity | I488: 2016 | J488: Refrigeration ClassTF4 Electricity 2016 | K488: RESELC | L488: RESAPALMOldREEUE | M488: RESAPALMOldRETF4ELC20 | N488: 1 | O488: 2020 | P488: 1073.036 | Q488: 1.892911 | R488: TJa | S488: 566.8708 | T488: 358 | U488: kWh/yr | V488: 1 | W488: 11.626 | X488: 21.895261 | Y488: 17 | Z488: 0.65 | AA488: 1
A489: Residential | B489: Apartment | C489: Lower-middle Income | D489: Old | E489: Refrigeration | G489: SF1 | H489: Electricity | I489: 2016 | J489: Refrigeration ClassSF1 Electricity 2016 | K489: RESELC | L489: RESAPALMOldREEUE | M489: RESAPALMOldRESF1ELC20 | N489: 1 | O489: 2020 | P489: 1597.3604 | Q489: 1.892911 | R489: TJa | S489: 843.86449 | T489: 705.226 | U489: kWh/yr | V489: 1.969905 | W489: 11.626 | X489: 21.895261 | Y489: 17 | Z489: 0.65 | AA489: 1
A490: Residential | B490: Apartment | C490: Lower-middle Income | D490: Old | E490: Refrigeration | G490: SF2 | H490: Electricity | I490: 2016 | J490: Refrigeration ClassSF2 Electricity 2016 | K490: RESELC | L490: RESAPALMOldREEUE | M490: RESAPALMOldRESF2ELC20 | N490: 1 | O490: 2020 | P490: 1731.4899 | Q490: 1.892911 | R490: TJa | S490: 914.72334 | T490: 671 | U490: kWh/yr | V490: 1.8743017 | W490: 11.626 | X490: 21.895261 | Y490: 17 | Z490: 0.65 | AA490: 1
A491: Residential | B491: Apartment | C491: Lower-middle Income | D491: Old | E491: Refrigeration | G491: SF3 | H491: Electricity | I491: 2016 | J491: Refrigeration ClassSF3 Electricity 2016 | K491: RESELC | L491: RESAPALMOldREEUE | M491: RESAPALMOldRESF3ELC20 | N491: 1 | O491: 2020 | P491: 1890.0066 | Q491: 1.892911 | R491: TJa | S491: 998.46562 | T491: 634.7034 | U491: kWh/yr | V491: 1.7729145 | W491: 11.626 | X491: 21.895261 | Y491: 17 | Z491: 0.65 | AA491: 1
A492: Residential | B492: Apartment | C492: Lower-middle Income | D492: Old | E492: Refrigeration | G492: SF4 | H492: Electricity | I492: 2016 | J492: Refrigeration ClassSF4 Electricity 2016 | K492: RESELC | L492: RESAPALMOldREEUE | M492: RESAPALMOldRESF4ELC20 | N492: 1 | O492: 2020 | P492: 2414.331 | Q492: 1.892911 | R492: TJa | S492: 1275.4593 | T492: 509 | U492: kWh/yr | V492: 1.4217877 | W492: 11.626 | X492: 21.895261 | Y492: 17 | Z492: 0.65 | AA492: 1
A493: Residential | B493: Apartment | C493: Lower-middle Income | D493: Old | E493: Refrigeration | G493: BF1 | H493: Electricity | I493: 2016 | J493: Refrigeration ClassBF1 Electricity 2016 | K493: RESELC | L493: RESAPALMOldREEUE | M493: RESAPALMOldREBF1ELC20 | N493: 1 | O493: 2020 | P493: 1255.9398 | Q493: 1.892911 | R493: TJa | S493: 663.49651 | T493: 520.55 | U493: kWh/yr | V493: 1.4540503 | W493: 11.626 | X493: 21.895261 | Y493: 17 | Z493: 0.65 | AA493: 1
A494: Residential | B494: Apartment | C494: Lower-middle Income | D494: Old | E494: Refrigeration | G494: BF2 | H494: Electricity | I494: 2016 | J494: Refrigeration ClassBF2 Electricity 2016 | K494: RESELC | L494: RESAPALMOldREEUE | M494: RESAPALMOldREBF2ELC20 | N494: 1 | O494: 2020 | P494: 1365.6822 | Q494: 1.892911 | R494: TJa | S494: 721.47193 | T494: 480 | U494: kWh/yr | V494: 1.3407821 | W494: 11.626 | X494: 21.895261 | Y494: 17 | Z494: 0.65 | AA494: 1
A495: Residential | B495: Apartment | C495: Lower-middle Income | D495: Old | E495: Refrigeration | G495: BF3 | H495: Electricity | I495: 2016 | J495: Refrigeration ClassBF3 Electricity 2016 | K495: RESELC | L495: RESAPALMOldREEUE | M495: RESAPALMOldREBF3ELC20 | N495: 1 | O495: 2020 | P495: 1414.4565 | Q495: 1.892911 | R495: TJa | S495: 747.23879 | T495: 469 | U495: kWh/yr | V495: 1.3100559 | W495: 11.626 | X495: 21.895261 | Y495: 17 | Z495: 0.65 | AA495: 1
A496: Residential | B496: Apartment | C496: Lower-middle Income | D496: Old | E496: Refrigeration | G496: BF4 | H496: Electricity | I496: 2016 | J496: Refrigeration ClassBF4 Electricity 2016 | K496: RESELC | L496: RESAPALMOldREEUE | M496: RESAPALMOldREBF4ELC20 | N496: 1 | O496: 2020 | P496: 1414.4565 | Q496: 1.892911 | R496: TJa | S496: 747.23879 | T496: 469 | U496: kWh/yr | V496: 1.3100559 | W496: 11.626 | X496: 21.895261 | Y496: 17 | Z496: 0.65 | AA496: 1
... A559: Residential | B559: House | C559: Lower-middle Income | D559: Old | E559: Water heating | G559: 2 | H559: Solar | I559: 2024 | J559: Water heating Class2 Solar 2024 | K559: RESSOL | L559: RESHOULMOldWHEUE | M559: RESHOULMOldWH2SOL24 | N559: 1 | O559: 2024 | P559: 13412.95 | Q559: 1.8663619 | R559: MW | S559: 7186.6822 | T559: 1 | U559: SEF | V559: 1 | W559: 15 | X559: 30 | Y559: 23 | Z559: 0.24 | AA559: 31.536
A560: Residential | B560: House | C560: Lower-middle Income | D560: Old | E560: Space heating | F560: Air HP | G560: 1 | H560: Electricity | I560: 2016 | J560: Space heating Air HP Class1 Electricity 2016 | K560: RESELC | L560: RESHOULMOldSHEUE | M560: RESHOULMOldSHAHP1ELC20 | N560: 1 | O560: 2020 | P560: 2956.9458 | Q560: 16.265241 | R560: MW | S560: 181.79539 | T560: 2.4032825 | U560: COP | V560: 2.4032825 | W560: 9 | X560: 22 | Y560: 16 | Z560: 0.082638123 | AA560: 31.536
A561: Residential | B561: House | C561: Lower-middle Income | D561: Old | E561: Space heating | F561: Air HP | G561: 1 | H561: Electricity | I561: 2023 | J561: Space heating Air HP Class1 Electricity 2023 | K561: RESELC | L561: RESHOULMOldSHEUE | M561: RESHOULMOldSHAHP1ELC23 | N561: 1 | O561: 2023 | P561: 2956.9458 | Q561: 16.265241 | R561: MW | S561: 181.79539 | T561: 2.4032825 | U561: COP | V561: 2.4032825 | W561: 9 | X561: 22 | Y561: 16 | Z561: 0.082638123 | AA561: 31.536
A562: Residential | B562: House | C562: Lower-middle Income | D562: Old | E562: Space heating | F562: Air HP | G562: 2 | H562: Electricity | I562: 2016 | J562: Space heating Air HP Class2 Electricity 2016 | K562: RESELC | L562: RESHOULMOldSHEUE | M562: RESHOULMOldSHAHP2ELC20 | N562: 1 | O562: 2020 | P562: 3109.3656 | Q562: 16.265241 | R562: MW | S562: 191.16628 | T562: 2.5205158 | U562: COP | V562: 2.5205158 | W562: 9 | X562: 22 | Y562: 16 | Z562: 0.082638123 | AA562: 31.536
A563: Residential | B563: House | C563: Lower-middle Income | D563: Old | E563: Space heating | F563: Air HP | G563: 2 | H563: Electricity | I563: 2023 | J563: Space heating Air HP Class2 Electricity 2023 | K563: RESELC | L563: RESHOULMOldSHEUE | M563: RESHOULMOldSHAHP2ELC23 | N563: 1 | O563: 2023 | P563: 3139.8496 | Q563: 16.265241 | R563: MW | S563: 193.04046 | T563: 2.5791325 | U563: COP | V563: 2.5791325 | W563: 9 | X563: 22 | Y563: 16 | Z563: 0.082638123 | AA563: 31.536
A564: Residential | B564: House | C564: Lower-middle Income | D564: Old | E564: Space heating | F564: Air HP | G564: 3 | H564: Electricity | I564: 2016 | J564: Space heating Air HP Class3 Electricity 2016 | K564: RESELC | L564: RESHOULMOldSHEUE | M564: RESHOULMOldSHAHP3ELC20 | N564: 1 | O564: 2020 | P564: 3017.9137 | Q564: 16.265241 | R564: MW | S564: 185.54375 | T564: 2.4912075 | U564: COP | V564: 2.4912075 | W564: 9 | X564: 22 | Y564: 16 | Z564: 0.082638123 | AA564: 31.536
A565: Residential | B565: House | C565: Lower-middle Income | D565: Old | E565: Space heating | F565: Air HP | G565: 3 | H565: Electricity | I565: 2022 | J565: Space heating Air HP Class3 Electricity 2022 | K565: RESELC | L565: RESHOULMOldSHEUE | M565: RESHOULMOldSHAHP3ELC22 | N565: 1 | O565: 2022 | P565: 3017.9137 | Q565: 16.265241 | R565: MW | S565: 185.54375 | T565: 2.4912075 | U565: COP | V565: 2.4912075 | W565: 9 | X565: 22 | Y565: 16 | Z565: 0.082638123 | AA565: 31.536
A566: Residential | B566: House | C566: Lower-middle Income | D566: Old | E566: Space heating | F566: Air HP | G566: 3 | H566: Electricity | I566: 2023 | J566: Space heating Air HP Class3 Electricity 2023 | K566: RESELC | L566: RESHOULMOldSHEUE | M566: RESHOULMOldSHAHP3ELC23 | N566: 1 | O566: 2023 | P566: 3266.4478 | Q566: 16.265241 | R566: MW | S566: 200.82382 | T566: 2.6963658 | U566: COP | V566: 2.6963658 | W566: 9 | X566: 22 | Y566: 16 | Z566: 0.082638123 | AA566: 31.536
A567: Residential | B567: House | C567: Lower-middle Income | D567: Old | E567: Space heating | F567: Air HP | G567: 4 | H567: Electricity | I567: 2016 | J567: Space heating Air HP Class4 Electricity 2016 | K567: RESELC | L567: RESHOULMOldSHEUE | M567: RESHOULMOldSHAHP4ELC20 | N567: 1 | O567: 2020 | P567: 3719.0452 | Q567: 16.265241 | R567: MW | S567: 228.64987 | T567: 2.6377491 | U567: COP | V567: 2.6377491 | W567: 9 | X567: 22 | Y567: 16 | Z567: 0.082638123 | AA567: 31.536
...

Sheet >> TIMES

Sheet Def_Tech
B2: ~FI_Process
B3: Sets | C3: TechName | D3: TechDesc | E3: Tact | F3: Tcap | G3: Tslvl | H3: PrimaryCG | I3: Vintage
B4: *Process Set Membership | C4: Technology Name | D4: Technology Description | E4: Activity Unit | F4: Capacity Unit | G4: TimeSlice level of Process Activity | H4: Primary Commodity Group | I4: Vintage Tracking
B5: =IF('RES TECH'!N3=1,"PRE","*") -> PRE | C5: ='RES TECH'!M3 -> RESAPALOOldWH1NGA20 | D5: =_xlfn.XLOOKUP($C5,'RES TECH'!$M:$M,'RES TECH'!$A:$A)&" "&_xlfn.XLOOKUP($C5,'RES TECH'!$M:$M,'RES TECH'!$B:$B)&" "&_xlfn.XLOOKUP($C5,'RES TECH'!$M:$M,'RES TECH'!$C:$C)&" "&_xlfn.XLOOKUP($C5,'RES TECH'!$M:$M,'RES TECH'!$D:$D)&" "&_xlfn.XLOOKUP($C5,'RES TECH'!$M:$M,'RES TECH'!$E:$E)&" "&_xlfn.XLOOKUP($C5,'RES TECH'!$M:$M,'RES TECH'!$F:$F)&" "&_xlfn.XLOOKUP($C5,'RES TECH'!$M:$M,'RES TECH'!$G:$G)&" "&_xlfn.XLOOKUP($C5,'RES TECH'!$M:$M,'RES TECH'!$H:$H) -> Residential Apartment Low Income Old Water heating 1 Natural gas | E5: =IF(F5="*","*",IF(F5="Mlma","Mlm","TJ")) -> TJ | F5: =IF(B5="*","*",_xlfn.XLOOKUP($C5,'RES TECH'!$M:$M,'RES TECH'!$R:$R)) -> MW
B6: =IF('RES TECH'!N4=1,"PRE","*") -> PRE | C6: ='RES TECH'!M4 -> RESAPALOOldWH2NGA20 | D6: =_xlfn.XLOOKUP($C6,'RES TECH'!$M:$M,'RES TECH'!$A:$A)&" "&_xlfn.XLOOKUP($C6,'RES TECH'!$M:$M,'RES TECH'!$B:$B)&" "&_xlfn.XLOOKUP($C6,'RES TECH'!$M:$M,'RES TECH'!$C:$C)&" "&_xlfn.XLOOKUP($C6,'RES TECH'!$M:$M,'RES TECH'!$D:$D)&" "&_xlfn.XLOOKUP($C6,'RES TECH'!$M:$M,'RES TECH'!$E:$E)&" "&_xlfn.XLOOKUP($C6,'RES TECH'!$M:$M,'RES TECH'!$F:$F)&" "&_xlfn.XLOOKUP($C6,'RES TECH'!$M:$M,'RES TECH'!$G:$G)&" "&_xlfn.XLOOKUP($C6,'RES TECH'!$M:$M,'RES TECH'!$H:$H) -> Residential Apartment Low Income Old Water heating 2 Natural gas | E6: =IF(F6="*","*",IF(F6="Mlma","Mlm","TJ")) -> TJ | F6: =IF(B6="*","*",_xlfn.XLOOKUP($C6,'RES TECH'!$M:$M,'RES TECH'!$R:$R)) -> MW
B7: =IF('RES TECH'!N5=1,"PRE","*") -> PRE | C7: ='RES TECH'!M5 -> RESAPALOOldWH3NGA20 | D7: =_xlfn.XLOOKUP($C7,'RES TECH'!$M:$M,'RES TECH'!$A:$A)&" "&_xlfn.XLOOKUP($C7,'RES TECH'!$M:$M,'RES TECH'!$B:$B)&" "&_xlfn.XLOOKUP($C7,'RES TECH'!$M:$M,'RES TECH'!$C:$C)&" "&_xlfn.XLOOKUP($C7,'RES TECH'!$M:$M,'RES TECH'!$D:$D)&" "&_xlfn.XLOOKUP($C7,'RES TECH'!$M:$M,'RES TECH'!$E:$E)&" "&_xlfn.XLOOKUP($C7,'RES TECH'!$M:$M,'RES TECH'!$F:$F)&" "&_xlfn.XLOOKUP($C7,'RES TECH'!$M:$M,'RES TECH'!$G:$G)&" "&_xlfn.XLOOKUP($C7,'RES TECH'!$M:$M,'RES TECH'!$H:$H) -> Residential Apartment Low Income Old Water heating 3 Natural gas | E7: =IF(F7="*","*",IF(F7="Mlma","Mlm","TJ")) -> TJ | F7: =IF(B7="*","*",_xlfn.XLOOKUP($C7,'RES TECH'!$M:$M,'RES TECH'!$R:$R)) -> MW
B8: =IF('RES TECH'!N6=1,"PRE","*") -> PRE | C8: ='RES TECH'!M6 -> RESAPALOOldWH3NGA23 | D8: =_xlfn.XLOOKUP($C8,'RES TECH'!$M:$M,'RES TECH'!$A:$A)&" "&_xlfn.XLOOKUP($C8,'RES TECH'!$M:$M,'RES TECH'!$B:$B)&" "&_xlfn.XLOOKUP($C8,'RES TECH'!$M:$M,'RES TECH'!$C:$C)&" "&_xlfn.XLOOKUP($C8,'RES TECH'!$M:$M,'RES TECH'!$D:$D)&" "&_xlfn.XLOOKUP($C8,'RES TECH'!$M:$M,'RES TECH'!$E:$E)&" "&_xlfn.XLOOKUP($C8,'RES TECH'!$M:$M,'RES TECH'!$F:$F)&" "&_xlfn.XLOOKUP($C8,'RES TECH'!$M:$M,'RES TECH'!$G:$G)&" "&_xlfn.XLOOKUP($C8,'RES TECH'!$M:$M,'RES TECH'!$H:$H) -> Residential Apartment Low Income Old Water heating 3 Natural gas | E8: =IF(F8="*","*",IF(F8="Mlma","Mlm","TJ")) -> TJ | F8: =IF(B8="*","*",_xlfn.XLOOKUP($C8,'RES TECH'!$M:$M,'RES TECH'!$R:$R)) -> MW
B9: =IF('RES TECH'!N7=1,"PRE","*") -> * | C9: ='RES TECH'!M7 -> RESAPALOOldWH4NGA20 | D9: =_xlfn.XLOOKUP($C9,'RES TECH'!$M:$M,'RES TECH'!$A:$A)&" "&_xlfn.XLOOKUP($C9,'RES TECH'!$M:$M,'RES TECH'!$B:$B)&" "&_xlfn.XLOOKUP($C9,'RES TECH'!$M:$M,'RES TECH'!$C:$C)&" "&_xlfn.XLOOKUP($C9,'RES TECH'!$M:$M,'RES TECH'!$D:$D)&" "&_xlfn.XLOOKUP($C9,'RES TECH'!$M:$M,'RES TECH'!$E:$E)&" "&_xlfn.XLOOKUP($C9,'RES TECH'!$M:$M,'RES TECH'!$F:$F)&" "&_xlfn.XLOOKUP($C9,'RES TECH'!$M:$M,'RES TECH'!$G:$G)&" "&_xlfn.XLOOKUP($C9,'RES TECH'!$M:$M,'RES TECH'!$H:$H) -> Residential Apartment Low Income Old Water heating 4 Natural gas | E9: =IF(F9="*","*",IF(F9="Mlma","Mlm","TJ")) -> * | F9: =IF(B9="*","*",_xlfn.XLOOKUP($C9,'RES TECH'!$M:$M,'RES TECH'!$R:$R)) -> *
B10: =IF('RES TECH'!N8=1,"PRE","*") -> PRE | C10: ='RES TECH'!M8 -> RESAPALOOldWH4NGA20 | D10: =_xlfn.XLOOKUP($C10,'RES TECH'!$M:$M,'RES TECH'!$A:$A)&" "&_xlfn.XLOOKUP($C10,'RES TECH'!$M:$M,'RES TECH'!$B:$B)&" "&_xlfn.XLOOKUP($C10,'RES TECH'!$M:$M,'RES TECH'!$C:$C)&" "&_xlfn.XLOOKUP($C10,'RES TECH'!$M:$M,'RES TECH'!$D:$D)&" "&_xlfn.XLOOKUP($C10,'RES TECH'!$M:$M,'RES TECH'!$E:$E)&" "&_xlfn.XLOOKUP($C10,'RES TECH'!$M:$M,'RES TECH'!$F:$F)&" "&_xlfn.XLOOKUP($C10,'RES TECH'!$M:$M,'RES TECH'!$G:$G)&" "&_xlfn.XLOOKUP($C10,'RES TECH'!$M:$M,'RES TECH'!$H:$H) -> Residential Apartment Low Income Old Water heating 4 Natural gas | E10: =IF(F10="*","*",IF(F10="Mlma","Mlm","TJ")) -> TJ | F10: =IF(B10="*","*",_xlfn.XLOOKUP($C10,'RES TECH'!$M:$M,'RES TECH'!$R:$R)) -> MW
B11: =IF('RES TECH'!N9=1,"PRE","*") -> PRE | C11: ='RES TECH'!M9 -> RESAPALOOldWH4NGA22 | D11: =_xlfn.XLOOKUP($C11,'RES TECH'!$M:$M,'RES TECH'!$A:$A)&" "&_xlfn.XLOOKUP($C11,'RES TECH'!$M:$M,'RES TECH'!$B:$B)&" "&_xlfn.XLOOKUP($C11,'RES TECH'!$M:$M,'RES TECH'!$C:$C)&" "&_xlfn.XLOOKUP($C11,'RES TECH'!$M:$M,'RES TECH'!$D:$D)&" "&_xlfn.XLOOKUP($C11,'RES TECH'!$M:$M,'RES TECH'!$E:$E)&" "&_xlfn.XLOOKUP($C11,'RES TECH'!$M:$M,'RES TECH'!$F:$F)&" "&_xlfn.XLOOKUP($C11,'RES TECH'!$M:$M,'RES TECH'!$G:$G)&" "&_xlfn.XLOOKUP($C11,'RES TECH'!$M:$M,'RES TECH'!$H:$H) -> Residential Apartment Low Income Old Water heating 4 Natural gas | E11: =IF(F11="*","*",IF(F11="Mlma","Mlm","TJ")) -> TJ | F11: =IF(B11="*","*",_xlfn.XLOOKUP($C11,'RES TECH'!$M:$M,'RES TECH'!$R:$R)) -> MW
B12: =IF('RES TECH'!N10=1,"PRE","*") -> PRE | C12: ='RES TECH'!M10 -> RESAPALOOldWH1ELC20 | D12: =_xlfn.XLOOKUP($C12,'RES TECH'!$M:$M,'RES TECH'!$A:$A)&" "&_xlfn.XLOOKUP($C12,'RES TECH'!$M:$M,'RES TECH'!$B:$B)&" "&_xlfn.XLOOKUP($C12,'RES TECH'!$M:$M,'RES TECH'!$C:$C)&" "&_xlfn.XLOOKUP($C12,'RES TECH'!$M:$M,'RES TECH'!$D:$D)&" "&_xlfn.XLOOKUP($C12,'RES TECH'!$M:$M,'RES TECH'!$E:$E)&" "&_xlfn.XLOOKUP($C12,'RES TECH'!$M:$M,'RES TECH'!$F:$F)&" "&_xlfn.XLOOKUP($C12,'RES TECH'!$M:$M,'RES TECH'!$G:$G)&" "&_xlfn.XLOOKUP($C12,'RES TECH'!$M:$M,'RES TECH'!$H:$H) -> Residential Apartment Low Income Old Water heating 1 Electricity | E12: =IF(F12="*","*",IF(F12="Mlma","Mlm","TJ")) -> TJ | F12: =IF(B12="*","*",_xlfn.XLOOKUP($C12,'RES TECH'!$M:$M,'RES TECH'!$R:$R)) -> MW
B13: =IF('RES TECH'!N11=1,"PRE","*") -> PRE | C13: ='RES TECH'!M11 -> RESAPALOOldWH2ELC20 | D13: =_xlfn.XLOOKUP($C13,'RES TECH'!$M:$M,'RES TECH'!$A:$A)&" "&_xlfn.XLOOKUP($C13,'RES TECH'!$M:$M,'RES TECH'!$B:$B)&" "&_xlfn.XLOOKUP($C13,'RES TECH'!$M:$M,'RES TECH'!$C:$C)&" "&_xlfn.XLOOKUP($C13,'RES TECH'!$M:$M,'RES TECH'!$D:$D)&" "&_xlfn.XLOOKUP($C13,'RES TECH'!$M:$M,'RES TECH'!$E:$E)&" "&_xlfn.XLOOKUP($C13,'RES TECH'!$M:$M,'RES TECH'!$F:$F)&" "&_xlfn.XLOOKUP($C13,'RES TECH'!$M:$M,'RES TECH'!$G:$G)&" "&_xlfn.XLOOKUP($C13,'RES TECH'!$M:$M,'RES TECH'!$H:$H) -> Residential Apartment Low Income Old Water heating 2 Electricity | E13: =IF(F13="*","*",IF(F13="Mlma","Mlm","TJ")) -> TJ | F13: =IF(B13="*","*",_xlfn.XLOOKUP($C13,'RES TECH'!$M:$M,'RES TECH'!$R:$R)) -> MW
B14: =IF('RES TECH'!N12=1,"PRE","*") -> PRE | C14: ='RES TECH'!M12 -> RESAPALOOldWH4ELC20 | D14: =_xlfn.XLOOKUP($C14,'RES TECH'!$M:$M,'RES TECH'!$A:$A)&" "&_xlfn.XLOOKUP($C14,'RES TECH'!$M:$M,'RES TECH'!$B:$B)&" "&_xlfn.XLOOKUP($C14,'RES TECH'!$M:$M,'RES TECH'!$C:$C)&" "&_xlfn.XLOOKUP($C14,'RES TECH'!$M:$M,'RES TECH'!$D:$D)&" "&_xlfn.XLOOKUP($C14,'RES TECH'!$M:$M,'RES TECH'!$E:$E)&" "&_xlfn.XLOOKUP($C14,'RES TECH'!$M:$M,'RES TECH'!$F:$F)&" "&_xlfn.XLOOKUP($C14,'RES TECH'!$M:$M,'RES TECH'!$G:$G)&" "&_xlfn.XLOOKUP($C14,'RES TECH'!$M:$M,'RES TECH'!$H:$H) -> Residential Apartment Low Income Old Water heating 4 Electricity | E14: =IF(F14="*","*",IF(F14="Mlma","Mlm","TJ")) -> TJ | F14: =IF(B14="*","*",_xlfn.XLOOKUP($C14,'RES TECH'!$M:$M,'RES TECH'!$R:$R)) -> MW
B15: =IF('RES TECH'!N13=1,"PRE","*") -> PRE | C15: ='RES TECH'!M13 -> RESAPALOOldWH5ELC20 | D15: =_xlfn.XLOOKUP($C15,'RES TECH'!$M:$M,'RES TECH'!$A:$A)&" "&_xlfn.XLOOKUP($C15,'RES TECH'!$M:$M,'RES TECH'!$B:$B)&" "&_xlfn.XLOOKUP($C15,'RES TECH'!$M:$M,'RES TECH'!$C:$C)&" "&_xlfn.XLOOKUP($C15,'RES TECH'!$M:$M,'RES TECH'!$D:$D)&" "&_xlfn.XLOOKUP($C15,'RES TECH'!$M:$M,'RES TECH'!$E:$E)&" "&_xlfn.XLOOKUP($C15,'RES TECH'!$M:$M,'RES TECH'!$F:$F)&" "&_xlfn.XLOOKUP($C15,'RES TECH'!$M:$M,'RES TECH'!$G:$G)&" "&_xlfn.XLOOKUP($C15,'RES TECH'!$M:$M,'RES TECH'!$H:$H) -> Residential Apartment Low Income Old Water heating 5 Electricity | E15: =IF(F15="*","*",IF(F15="Mlma","Mlm","TJ")) -> TJ | F15: =IF(B15="*","*",_xlfn.XLOOKUP($C15,'RES TECH'!$M:$M,'RES TECH'!$R:$R)) -> MW
B16: =IF('RES TECH'!N14=1,"PRE","*") -> PRE | C16: ='RES TECH'!M14 -> RESAPALOOldWH5ELC22 | D16: =_xlfn.XLOOKUP($C16,'RES TECH'!$M:$M,'RES TECH'!$A:$A)&" "&_xlfn.XLOOKUP($C16,'RES TECH'!$M:$M,'RES TECH'!$B:$B)&" "&_xlfn.XLOOKUP($C16,'RES TECH'!$M:$M,'RES TECH'!$C:$C)&" "&_xlfn.XLOOKUP($C16,'RES TECH'!$M:$M,'RES TECH'!$D:$D)&" "&_xlfn.XLOOKUP($C16,'RES TECH'!$M:$M,'RES TECH'!$E:$E)&" "&_xlfn.XLOOKUP($C16,'RES TECH'!$M:$M,'RES TECH'!$F:$F)&" "&_xlfn.XLOOKUP($C16,'RES TECH'!$M:$M,'RES TECH'!$G:$G)&" "&_xlfn.XLOOKUP($C16,'RES TECH'!$M:$M,'RES TECH'!$H:$H) -> Residential Apartment Low Income Old Water heating 5 Electricity | E16: =IF(F16="*","*",IF(F16="Mlma","Mlm","TJ")) -> TJ | F16: =IF(B16="*","*",_xlfn.XLOOKUP($C16,'RES TECH'!$M:$M,'RES TECH'!$R:$R)) -> MW
... B3320: =IF('RES TECH'!N3318=1,"PRE","*") -> PRE | C3320: ='RES TECH'!M3318 -> RESHOUHINewOENGA20 | D3320: =_xlfn.XLOOKUP($C3320,'RES TECH'!$M:$M,'RES TECH'!$A:$A)&" "&_xlfn.XLOOKUP($C3320,'RES TECH'!$M:$M,'RES TECH'!$B:$B)&" "&_xlfn.XLOOKUP($C3320,'RES TECH'!$M:$M,'RES TECH'!$C:$C)&" "&_xlfn.XLOOKUP($C3320,'RES TECH'!$M:$M,'RES TECH'!$D:$D)&" "&_xlfn.XLOOKUP($C3320,'RES TECH'!$M:$M,'RES TECH'!$E:$E)&" "&_xlfn.XLOOKUP($C3320,'RES TECH'!$M:$M,'RES TECH'!$F:$F)&" "&_xlfn.XLOOKUP($C3320,'RES TECH'!$M:$M,'RES TECH'!$G:$G)&" "&_xlfn.XLOOKUP($C3320,'RES TECH'!$M:$M,'RES TECH'!$H:$H) -> Residential House High Income New Other end use Natural gas | E3320: =IF(F3320="*","*",IF(F3320="Mlma","Mlm","TJ")) -> TJ | F3320: =IF(B3320="*","*",_xlfn.XLOOKUP($C3320,'RES TECH'!$M:$M,'RES TECH'!$R:$R)) -> TJa

Sheet Def_Comm
B2: ~FI_Comm
B3: Csets | C3: CommName | D3: CommDesc | E3: Unit | F3: LimType | G3: CTSLvl | H3: PeakTS | I3: Ctype
B4: *Commodity Set Membership | C4: Commodity Name | D4: Commodity Description | E4: Unit | F4: Sense of the Balance EQN. | G4: Timeslice Level | H4: Peak Monitoring | I4: Electricity Indicator

Sheet TECH RES
D4: ~FI_T
B5: TechName | C5: Comm-IN | D5: Comm-OUT | E5: NCAP_START | F5: NCAP_TLIFE | G5: EFF | H5: PRC_CAPACT | I5: NCAP_AFA | J5: NCAP_COST | K5: NCAP_FOM | L5: *NCAP_FOM | M5: NCAP_DRATE
B6: * | F6: Yr | G6: Out/In | H6: TJ/MW | I6: % | J6: $ /kW | K6: $ /kW / Yr | L6: $ /kW / Yr | M6: %
B7: =IF('RES TECH'!N3=1,'RES TECH'!M3,"*") -> RESAPALOOldWH1NGA20 | C7: =IF(B7="*","*",_xlfn.XLOOKUP(B7,'RES TECH'!M:M,'RES TECH'!K:K)) -> RESNGA | D7: =IF(B7="*","*",_xlfn.XLOOKUP(B7,'RES TECH'!M:M,'RES TECH'!L:L)) -> RESAPALOOldWHEUE | E7: =IF(B7="*","*",_xlfn.XLOOKUP(B7,'RES TECH'!M:M,'RES TECH'!O:O)) -> 2020 | F7: =IF(B7="*","*",_xlfn.XLOOKUP(B7,'RES TECH'!M:M,'RES TECH'!Y:Y)) -> 14 | G7: =IF(B7="*","*",_xlfn.XLOOKUP(B7,'RES TECH'!M:M,'RES TECH'!V:V)) -> 0.61015 | H7: =IF(B7="*","*",_xlfn.XLOOKUP(B7,'RES TECH'!M:M,'RES TECH'!AA:AA)) -> 31.536 | I7: =IF(B7="*","*",_xlfn.XLOOKUP(B7,'RES TECH'!M:M,'RES TECH'!Z:Z)) -> 0.24 | J7: =IF(B7="*","*",_xlfn.XLOOKUP(B7,'RES TECH'!M:M,'RES TECH'!S:S)) -> 1235.5639 | K7: =IF(B7="*","*",5%*J7) -> 61.778196 | L7: =IF(B7="*","*",5%*K7) -> 3.0889098 | M7: =IF(B7="*","*",IF(_xlfn.XLOOKUP(B7,'RES TECH'!$M:$M,'RES TECH'!$C:$C)="Low Income",IF(G7>1,IF(G7>3,0.3,0.24),0.12),IF(_xlfn.XLOOKUP(B7,'RES TECH'!$M:$M,'RES TECH'!$C:$C)="Lower-middle Income",IF(G7>1,IF(G7>3,0.23,0.18),0.09),IF(_xlfn.XLOOKUP(B7,'RES TECH'!$M:$M,'RES TECH'!$C:$C)="Upper-middle Income",IF(G7>1,IF(G7>3,0.15,0.12),0.06),IF(_xlfn.XLOOKUP(B7,'RES TECH'!$M:$M,'RES TECH'!$C:$C)="High Income",IF(G7>1,IF(G7>3,0.08,0.06),0.03)))))) -> 0.12
B8: =IF('RES TECH'!N4=1,'RES TECH'!M4,"*") -> RESAPALOOldWH2NGA20 | C8: =IF(B8="*","*",_xlfn.XLOOKUP(B8,'RES TECH'!M:M,'RES TECH'!K:K)) -> RESNGA | D8: =IF(B8="*","*",_xlfn.XLOOKUP(B8,'RES TECH'!M:M,'RES TECH'!L:L)) -> RESAPALOOldWHEUE | E8: =IF(B8="*","*",_xlfn.XLOOKUP(B8,'RES TECH'!M:M,'RES TECH'!O:O)) -> 2020 | F8: =IF(B8="*","*",_xlfn.XLOOKUP(B8,'RES TECH'!M:M,'RES TECH'!Y:Y)) -> 14 | G8: =IF(B8="*","*",_xlfn.XLOOKUP(B8,'RES TECH'!M:M,'RES TECH'!V:V)) -> 0.63 | H8: =IF(B8="*","*",_xlfn.XLOOKUP(B8,'RES TECH'!M:M,'RES TECH'!AA:AA)) -> 31.536 | I8: =IF(B8="*","*",_xlfn.XLOOKUP(B8,'RES TECH'!M:M,'RES TECH'!Z:Z)) -> 0.24 | J8: =IF(B8="*","*",_xlfn.XLOOKUP(B8,'RES TECH'!M:M,'RES TECH'!S:S)) -> 1303.266 | K8: =IF(B8="*","*",5%*J8) -> 65.163302 | L8: =IF(B8="*","*",5%*K8) -> 3.2581651 | M8: =IF(B8="*","*",IF(_xlfn.XLOOKUP(B8,'RES TECH'!$M:$M,'RES TECH'!$C:$C)="Low Income",IF(G8>1,IF(G8>3,0.3,0.24),0.12),IF(_xlfn.XLOOKUP(B8,'RES TECH'!$M:$M,'RES TECH'!$C:$C)="Lower-middle Income",IF(G8>1,IF(G8>3,0.23,0.18),0.09),IF(_xlfn.XLOOKUP(B8,'RES TECH'!$M:$M,'RES TECH'!$C:$C)="Upper-middle Income",IF(G8>1,IF(G8>3,0.15,0.12),0.06),IF(_xlfn.XLOOKUP(B8,'RES TECH'!$M:$M,'RES TECH'!$C:$C)="High Income",IF(G8>1,IF(G8>3,0.08,0.06),0.03)))))) -> 0.12
B9: =IF('RES TECH'!N5=1,'RES TECH'!M5,"*") -> RESAPALOOldWH3NGA20 | C9: =IF(B9="*","*",_xlfn.XLOOKUP(B9,'RES TECH'!M:M,'RES TECH'!K:K)) -> RESNGA | D9: =IF(B9="*","*",_xlfn.XLOOKUP(B9,'RES TECH'!M:M,'RES TECH'!L:L)) -> RESAPALOOldWHEUE | E9: =IF(B9="*","*",_xlfn.XLOOKUP(B9,'RES TECH'!M:M,'RES TECH'!O:O)) -> 2020 | F9: =IF(B9="*","*",_xlfn.XLOOKUP(B9,'RES TECH'!M:M,'RES TECH'!Y:Y)) -> 14 | G9: =IF(B9="*","*",_xlfn.XLOOKUP(B9,'RES TECH'!M:M,'RES TECH'!V:V)) -> 0.66 | H9: =IF(B9="*","*",_xlfn.XLOOKUP(B9,'RES TECH'!M:M,'RES TECH'!AA:AA)) -> 31.536 | I9: =IF(B9="*","*",_xlfn.XLOOKUP(B9,'RES TECH'!M:M,'RES TECH'!Z:Z)) -> 0.24 | J9: =IF(B9="*","*",_xlfn.XLOOKUP(B9,'RES TECH'!M:M,'RES TECH'!S:S)) -> 1370.9682 | K9: =IF(B9="*","*",5%*J9) -> 68.548409 | L9: =IF(B9="*","*",5%*K9) -> 3.4274204 | M9: =IF(B9="*","*",IF(_xlfn.XLOOKUP(B9,'RES TECH'!$M:$M,'RES TECH'!$C:$C)="Low Income",IF(G9>1,IF(G9>3,0.3,0.24),0.12),IF(_xlfn.XLOOKUP(B9,'RES TECH'!$M:$M,'RES TECH'!$C:$C)="Lower-middle Income",IF(G9>1,IF(G9>3,0.23,0.18),0.09),IF(_xlfn.XLOOKUP(B9,'RES TECH'!$M:$M,'RES TECH'!$C:$C)="Upper-middle Income",IF(G9>1,IF(G9>3,0.15,0.12),0.06),IF(_xlfn.XLOOKUP(B9,'RES TECH'!$M:$M,'RES TECH'!$C:$C)="High Income",IF(G9>1,IF(G9>3,0.08,0.06),0.03)))))) -> 0.12
B10: =IF('RES TECH'!N6=1,'RES TECH'!M6,"*") -> RESAPALOOldWH3NGA23 | C10: =IF(B10="*","*",_xlfn.XLOOKUP(B10,'RES TECH'!M:M,'RES TECH'!K:K)) -> RESNGA | D10: =IF(B10="*","*",_xlfn.XLOOKUP(B10,'RES TECH'!M:M,'RES TECH'!L:L)) -> RESAPALOOldWHEUE | E10: =IF(B10="*","*",_xlfn.XLOOKUP(B10,'RES TECH'!M:M,'RES TECH'!O:O)) -> 2023 | F10: =IF(B10="*","*",_xlfn.XLOOKUP(B10,'RES TECH'!M:M,'RES TECH'!Y:Y)) -> 14 | G10: =IF(B10="*","*",_xlfn.XLOOKUP(B10,'RES TECH'!M:M,'RES TECH'!V:V)) -> 0.835 | H10: =IF(B10="*","*",_xlfn.XLOOKUP(B10,'RES TECH'!M:M,'RES TECH'!AA:AA)) -> 31.536 | I10: =IF(B10="*","*",_xlfn.XLOOKUP(B10,'RES TECH'!M:M,'RES TECH'!Z:Z)) -> 0.24 | J10: =IF(B10="*","*",_xlfn.XLOOKUP(B10,'RES TECH'!M:M,'RES TECH'!S:S)) -> 2146.0949 | K10: =IF(B10="*","*",5%*J10) -> 107.30475 | L10: =IF(B10="*","*",5%*K10) -> 5.3652373 | M10: =IF(B10="*","*",IF(_xlfn.XLOOKUP(B10,'RES TECH'!$M:$M,'RES TECH'!$C:$C)="Low Income",IF(G10>1,IF(G10>3,0.3,0.24),0.12),IF(_xlfn.XLOOKUP(B10,'RES TECH'!$M:$M,'RES TECH'!$C:$C)="Lower-middle Income",IF(G10>1,IF(G10>3,0.23,0.18),0.09),IF(_xlfn.XLOOKUP(B10,'RES TECH'!$M:$M,'RES TECH'!$C:$C)="Upper-middle Income",IF(G10>1,IF(G10>3,0.15,0.12),0.06),IF(_xlfn.XLOOKUP(B10,'RES TECH'!$M:$M,'RES TECH'!$C:$C)="High Income",IF(G10>1,IF(G10>3,0.08,0.06),0.03)))))) -> 0.12
B11: =IF('RES TECH'!N7=1,'RES TECH'!M7,"*") -> * | C11: =IF(B11="*","*",_xlfn.XLOOKUP(B11,'RES TECH'!M:M,'RES TECH'!K:K)) -> * | D11: =IF(B11="*","*",_xlfn.XLOOKUP(B11,'RES TECH'!M:M,'RES TECH'!L:L)) -> * | E11: =IF(B11="*","*",_xlfn.XLOOKUP(B11,'RES TECH'!M:M,'RES TECH'!O:O)) -> * | F11: =IF(B11="*","*",_xlfn.XLOOKUP(B11,'RES TECH'!M:M,'RES TECH'!Y:Y)) -> * | G11: =IF(B11="*","*",_xlfn.XLOOKUP(B11,'RES TECH'!M:M,'RES TECH'!V:V)) -> * | H11: =IF(B11="*","*",_xlfn.XLOOKUP(B11,'RES TECH'!M:M,'RES TECH'!AA:AA)) -> * | I11: =IF(B11="*","*",_xlfn.XLOOKUP(B11,'RES TECH'!M:M,'RES TECH'!Z:Z)) -> * | J11: =IF(B11="*","*",_xlfn.XLOOKUP(B11,'RES TECH'!M:M,'RES TECH'!S:S)) -> * | K11: =IF(B11="*","*",5%*J11) -> * | L11: =IF(B11="*","*",5%*K11) -> * | M11: =IF(B11="*","*",IF(_xlfn.XLOOKUP(B11,'RES TECH'!$M:$M,'RES TECH'!$C:$C)="Low Income",IF(G11>1,IF(G11>3,0.3,0.24),0.12),IF(_xlfn.XLOOKUP(B11,'RES TECH'!$M:$M,'RES TECH'!$C:$C)="Lower-middle Income",IF(G11>1,IF(G11>3,0.23,0.18),0.09),IF(_xlfn.XLOOKUP(B11,'RES TECH'!$M:$M,'RES TECH'!$C:$C)="Upper-middle Income",IF(G11>1,IF(G11>3,0.15,0.12),0.06),IF(_xlfn.XLOOKUP(B11,'RES TECH'!$M:$M,'RES TECH'!$C:$C)="High Income",IF(G11>1,IF(G11>3,0.08,0.06),0.03)))))) -> *
B12: =IF('RES TECH'!N8=1,'RES TECH'!M8,"*") -> RESAPALOOldWH4NGA20 | C12: =IF(B12="*","*",_xlfn.XLOOKUP(B12,'RES TECH'!M:M,'RES TECH'!K:K)) -> RESNGA | D12: =IF(B12="*","*",_xlfn.XLOOKUP(B12,'RES TECH'!M:M,'RES TECH'!L:L)) -> RESAPALOOldWHEUE | E12: =IF(B12="*","*",_xlfn.XLOOKUP(B12,'RES TECH'!M:M,'RES TECH'!O:O)) -> 2020 | F12: =IF(B12="*","*",_xlfn.XLOOKUP(B12,'RES TECH'!M:M,'RES TECH'!Y:Y)) -> 14 | G12: =IF(B12="*","*",_xlfn.XLOOKUP(B12,'RES TECH'!M:M,'RES TECH'!V:V)) -> 0.81 | H12: =IF(B12="*","*",_xlfn.XLOOKUP(B12,'RES TECH'!M:M,'RES TECH'!AA:AA)) -> 31.536 | I12: =IF(B12="*","*",_xlfn.XLOOKUP(B12,'RES TECH'!M:M,'RES TECH'!Z:Z)) -> 0.24 | J12: =IF(B12="*","*",_xlfn.XLOOKUP(B12,'RES TECH'!M:M,'RES TECH'!S:S)) -> 2081.8406 | K12: =IF(B12="*","*",5%*J12) -> 104.09203 | L12: =IF(B12="*","*",5%*K12) -> 5.2046014 | M12: =IF(B12="*","*",IF(_xlfn.XLOOKUP(B12,'RES TECH'!$M:$M,'RES TECH'!$C:$C)="Low Income",IF(G12>1,IF(G12>3,0.3,0.24),0.12),IF(_xlfn.XLOOKUP(B12,'RES TECH'!$M:$M,'RES TECH'!$C:$C)="Lower-middle Income",IF(G12>1,IF(G12>3,0.23,0.18),0.09),IF(_xlfn.XLOOKUP(B12,'RES TECH'!$M:$M,'RES TECH'!$C:$C)="Upper-middle Income",IF(G12>1,IF(G12>3,0.15,0.12),0.06),IF(_xlfn.XLOOKUP(B12,'RES TECH'!$M:$M,'RES TECH'!$C:$C)="High Income",IF(G12>1,IF(G12>3,0.08,0.06),0.03)))))) -> 0.12
B13: =IF('RES TECH'!N9=1,'RES TECH'!M9,"*") -> RESAPALOOldWH4NGA22 | C13: =IF(B13="*","*",_xlfn.XLOOKUP(B13,'RES TECH'!M:M,'RES TECH'!K:K)) -> RESNGA | D13: =IF(B13="*","*",_xlfn.XLOOKUP(B13,'RES TECH'!M:M,'RES TECH'!L:L)) -> RESAPALOOldWHEUE | E13: =IF(B13="*","*",_xlfn.XLOOKUP(B13,'RES TECH'!M:M,'RES TECH'!O:O)) -> 2022 | F13: =IF(B13="*","*",_xlfn.XLOOKUP(B13,'RES TECH'!M:M,'RES TECH'!Y:Y)) -> 14 | G13: =IF(B13="*","*",_xlfn.XLOOKUP(B13,'RES TECH'!M:M,'RES TECH'!V:V)) -> 0.81 | H13: =IF(B13="*","*",_xlfn.XLOOKUP(B13,'RES TECH'!M:M,'RES TECH'!AA:AA)) -> 31.536 | I13: =IF(B13="*","*",_xlfn.XLOOKUP(B13,'RES TECH'!M:M,'RES TECH'!Z:Z)) -> 0.24 | J13: =IF(B13="*","*",_xlfn.XLOOKUP(B13,'RES TECH'!M:M,'RES TECH'!S:S)) -> 2081.8406 | K13: =IF(B13="*","*",5%*J13) -> 104.09203 | L13: =IF(B13="*","*",5%*K13) -> 5.2046014 | M13: =IF(B13="*","*",IF(_xlfn.XLOOKUP(B13,'RES TECH'!$M:$M,'RES TECH'!$C:$C)="Low Income",IF(G13>1,IF(G13>3,0.3,0.24),0.12),IF(_xlfn.XLOOKUP(B13,'RES TECH'!$M:$M,'RES TECH'!$C:$C)="Lower-middle Income",IF(G13>1,IF(G13>3,0.23,0.18),0.09),IF(_xlfn.XLOOKUP(B13,'RES TECH'!$M:$M,'RES TECH'!$C:$C)="Upper-middle Income",IF(G13>1,IF(G13>3,0.15,0.12),0.06),IF(_xlfn.XLOOKUP(B13,'RES TECH'!$M:$M,'RES TECH'!$C:$C)="High Income",IF(G13>1,IF(G13>3,0.08,0.06),0.03)))))) -> 0.12
B14: =IF('RES TECH'!N10=1,'RES TECH'!M10,"*") -> RESAPALOOldWH1ELC20 | C14: =IF(B14="*","*",_xlfn.XLOOKUP(B14,'RES TECH'!M:M,'RES TECH'!K:K)) -> RESELC | D14: =IF(B14="*","*",_xlfn.XLOOKUP(B14,'RES TECH'!M:M,'RES TECH'!L:L)) -> RESAPALOOldWHEUE | E14: =IF(B14="*","*",_xlfn.XLOOKUP(B14,'RES TECH'!M:M,'RES TECH'!O:O)) -> 2020 | F14: =IF(B14="*","*",_xlfn.XLOOKUP(B14,'RES TECH'!M:M,'RES TECH'!Y:Y)) -> 14 | G14: =IF(B14="*","*",_xlfn.XLOOKUP(B14,'RES TECH'!M:M,'RES TECH'!V:V)) -> 0.91555 | H14: =IF(B14="*","*",_xlfn.XLOOKUP(B14,'RES TECH'!M:M,'RES TECH'!AA:AA)) -> 31.536 | I14: =IF(B14="*","*",_xlfn.XLOOKUP(B14,'RES TECH'!M:M,'RES TECH'!Z:Z)) -> 0.24 | J14: =IF(B14="*","*",_xlfn.XLOOKUP(B14,'RES TECH'!M:M,'RES TECH'!S:S)) -> 524.69152 | K14: =IF(B14="*","*",5%*J14) -> 26.234576 | L14: =IF(B14="*","*",5%*K14) -> 1.3117288 | M14: =IF(B14="*","*",IF(_xlfn.XLOOKUP(B14,'RES TECH'!$M:$M,'RES TECH'!$C:$C)="Low Income",IF(G14>1,IF(G14>3,0.3,0.24),0.12),IF(_xlfn.XLOOKUP(B14,'RES TECH'!$M:$M,'RES TECH'!$C:$C)="Lower-middle Income",IF(G14>1,IF(G14>3,0.23,0.18),0.09),IF(_xlfn.XLOOKUP(B14,'RES TECH'!$M:$M,'RES TECH'!$C:$C)="Upper-middle Income",IF(G14>1,IF(G14>3,0.15,0.12),0.06),IF(_xlfn.XLOOKUP(B14,'RES TECH'!$M:$M,'RES TECH'!$C:$C)="High Income",IF(G14>1,IF(G14>3,0.08,0.06),0.03)))))) -> 0.12
B15: =IF('RES TECH'!N11=1,'RES TECH'!M11,"*") -> RESAPALOOldWH2ELC20 | C15: =IF(B15="*","*",_xlfn.XLOOKUP(B15,'RES TECH'!M:M,'RES TECH'!K:K)) -> RESELC | D15: =IF(B15="*","*",_xlfn.XLOOKUP(B15,'RES TECH'!M:M,'RES TECH'!L:L)) -> RESAPALOOldWHEUE | E15: =IF(B15="*","*",_xlfn.XLOOKUP(B15,'RES TECH'!M:M,'RES TECH'!O:O)) -> 2020 | F15: =IF(B15="*","*",_xlfn.XLOOKUP(B15,'RES TECH'!M:M,'RES TECH'!Y:Y)) -> 14 | G15: =IF(B15="*","*",_xlfn.XLOOKUP(B15,'RES TECH'!M:M,'RES TECH'!V:V)) -> 0.93 | H15: =IF(B15="*","*",_xlfn.XLOOKUP(B15,'RES TECH'!M:M,'RES TECH'!AA:AA)) -> 31.536 | I15: =IF(B15="*","*",_xlfn.XLOOKUP(B15,'RES TECH'!M:M,'RES TECH'!Z:Z)) -> 0.24 | J15: =IF(B15="*","*",_xlfn.XLOOKUP(B15,'RES TECH'!M:M,'RES TECH'!S:S)) -> 575.46812 | K15: =IF(B15="*","*",5%*J15) -> 28.773406 | L15: =IF(B15="*","*",5%*K15) -> 1.4386703 | M15: =IF(B15="*","*",IF(_xlfn.XLOOKUP(B15,'RES TECH'!$M:$M,'RES TECH'!$C:$C)="Low Income",IF(G15>1,IF(G15>3,0.3,0.24),0.12),IF(_xlfn.XLOOKUP(B15,'RES TECH'!$M:$M,'RES TECH'!$C:$C)="Lower-middle Income",IF(G15>1,IF(G15>3,0.23,0.18),0.09),IF(_xlfn.XLOOKUP(B15,'RES TECH'!$M:$M,'RES TECH'!$C:$C)="Upper-middle Income",IF(G15>1,IF(G15>3,0.15,0.12),0.06),IF(_xlfn.XLOOKUP(B15,'RES TECH'!$M:$M,'RES TECH'!$C:$C)="High Income",IF(G15>1,IF(G15>3,0.08,0.06),0.03)))))) -> 0.12
B16: =IF('RES TECH'!N12=1,'RES TECH'!M12,"*") -> RESAPALOOldWH4ELC20 | C16: =IF(B16="*","*",_xlfn.XLOOKUP(B16,'RES TECH'!M:M,'RES TECH'!K:K)) -> RESELC | D16: =IF(B16="*","*",_xlfn.XLOOKUP(B16,'RES TECH'!M:M,'RES TECH'!L:L)) -> RESAPALOOldWHEUE | E16: =IF(B16="*","*",_xlfn.XLOOKUP(B16,'RES TECH'!M:M,'RES TECH'!O:O)) -> 2020 | F16: =IF(B16="*","*",_xlfn.XLOOKUP(B16,'RES TECH'!M:M,'RES TECH'!Y:Y)) -> 14 | G16: =IF(B16="*","*",_xlfn.XLOOKUP(B16,'RES TECH'!M:M,'RES TECH'!V:V)) -> 0.95 | H16: =IF(B16="*","*",_xlfn.XLOOKUP(B16,'RES TECH'!M:M,'RES TECH'!AA:AA)) -> 31.536 | I16: =IF(B16="*","*",_xlfn.XLOOKUP(B16,'RES TECH'!M:M,'RES TECH'!Z:Z)) -> 0.24 | J16: =IF(B16="*","*",_xlfn.XLOOKUP(B16,'RES TECH'!M:M,'RES TECH'!S:S)) -> 829.35112 | K16: =IF(B16="*","*",5%*J16) -> 41.467556 | L16: =IF(B16="*","*",5%*K16) -> 2.0733778 | M16: =IF(B16="*","*",IF(_xlfn.XLOOKUP(B16,'RES TECH'!$M:$M,'RES TECH'!$C:$C)="Low Income",IF(G16>1,IF(G16>3,0.3,0.24),0.12),IF(_xlfn.XLOOKUP(B16,'RES TECH'!$M:$M,'RES TECH'!$C:$C)="Lower-middle Income",IF(G16>1,IF(G16>3,0.23,0.18),0.09),IF(_xlfn.XLOOKUP(B16,'RES TECH'!$M:$M,'RES TECH'!$C:$C)="Upper-middle Income",IF(G16>1,IF(G16>3,0.15,0.12),0.06),IF(_xlfn.XLOOKUP(B16,'RES TECH'!$M:$M,'RES TECH'!$C:$C)="High Income",IF(G16>1,IF(G16>3,0.08,0.06),0.03)))))) -> 0.12
B17: =IF('RES TECH'!N13=1,'RES TECH'!M13,"*") -> RESAPALOOldWH5ELC20 | C17: =IF(B17="*","*",_xlfn.XLOOKUP(B17,'RES TECH'!M:M,'RES TECH'!K:K)) -> RESELC | D17: =IF(B17="*","*",_xlfn.XLOOKUP(B17,'RES TECH'!M:M,'RES TECH'!L:L)) -> RESAPALOOldWHEUE | E17: =IF(B17="*","*",_xlfn.XLOOKUP(B17,'RES TECH'!M:M,'RES TECH'!O:O)) -> 2020 | F17: =IF(B17="*","*",_xlfn.XLOOKUP(B17,'RES TECH'!M:M,'RES TECH'!Y:Y)) -> 14 | G17: =IF(B17="*","*",_xlfn.XLOOKUP(B17,'RES TECH'!M:M,'RES TECH'!V:V)) -> 3.28 | H17: =IF(B17="*","*",_xlfn.XLOOKUP(B17,'RES TECH'!M:M,'RES TECH'!AA:AA)) -> 31.536 | I17: =IF(B17="*","*",_xlfn.XLOOKUP(B17,'RES TECH'!M:M,'RES TECH'!Z:Z)) -> 0.24 | J17: =IF(B17="*","*",_xlfn.XLOOKUP(B17,'RES TECH'!M:M,'RES TECH'!S:S)) -> 1404.8192 | K17: =IF(B17="*","*",5%*J17) -> 70.240962 | L17: =IF(B17="*","*",5%*K17) -> 3.5120481 | M17: =IF(B17="*","*",IF(_xlfn.XLOOKUP(B17,'RES TECH'!$M:$M,'RES TECH'!$C:$C)="Low Income",IF(G17>1,IF(G17>3,0.3,0.24),0.12),IF(_xlfn.XLOOKUP(B17,'RES TECH'!$M:$M,'RES TECH'!$C:$C)="Lower-middle Income",IF(G17>1,IF(G17>3,0.23,0.18),0.09),IF(_xlfn.XLOOKUP(B17,'RES TECH'!$M:$M,'RES TECH'!$C:$C)="Upper-middle Income",IF(G17>1,IF(G17>3,0.15,0.12),0.06),IF(_xlfn.XLOOKUP(B17,'RES TECH'!$M:$M,'RES TECH'!$C:$C)="High Income",IF(G17>1,IF(G17>3,0.08,0.06),0.03)))))) -> 0.3
B18: =IF('RES TECH'!N14=1,'RES TECH'!M14,"*") -> RESAPALOOldWH5ELC22 | C18: =IF(B18="*","*",_xlfn.XLOOKUP(B18,'RES TECH'!M:M,'RES TECH'!K:K)) -> RESELC | D18: =IF(B18="*","*",_xlfn.XLOOKUP(B18,'RES TECH'!M:M,'RES TECH'!L:L)) -> RESAPALOOldWHEUE | E18: =IF(B18="*","*",_xlfn.XLOOKUP(B18,'RES TECH'!M:M,'RES TECH'!O:O)) -> 2022 | F18: =IF(B18="*","*",_xlfn.XLOOKUP(B18,'RES TECH'!M:M,'RES TECH'!Y:Y)) -> 14 | G18: =IF(B18="*","*",_xlfn.XLOOKUP(B18,'RES TECH'!M:M,'RES TECH'!V:V)) -> 3.28 | H18: =IF(B18="*","*",_xlfn.XLOOKUP(B18,'RES TECH'!M:M,'RES TECH'!AA:AA)) -> 31.536 | I18: =IF(B18="*","*",_xlfn.XLOOKUP(B18,'RES TECH'!M:M,'RES TECH'!Z:Z)) -> 0.24 | J18: =IF(B18="*","*",_xlfn.XLOOKUP(B18,'RES TECH'!M:M,'RES TECH'!S:S)) -> 1404.8192 | K18: =IF(B18="*","*",5%*J18) -> 70.240962 | L18: =IF(B18="*","*",5%*K18) -> 3.5120481 | M18: =IF(B18="*","*",IF(_xlfn.XLOOKUP(B18,'RES TECH'!$M:$M,'RES TECH'!$C:$C)="Low Income",IF(G18>1,IF(G18>3,0.3,0.24),0.12),IF(_xlfn.XLOOKUP(B18,'RES TECH'!$M:$M,'RES TECH'!$C:$C)="Lower-middle Income",IF(G18>1,IF(G18>3,0.23,0.18),0.09),IF(_xlfn.XLOOKUP(B18,'RES TECH'!$M:$M,'RES TECH'!$C:$C)="Upper-middle Income",IF(G18>1,IF(G18>3,0.15,0.12),0.06),IF(_xlfn.XLOOKUP(B18,'RES TECH'!$M:$M,'RES TECH'!$C:$C)="High Income",IF(G18>1,IF(G18>3,0.08,0.06),0.03)))))) -> 0.3
... B3322: =IF('RES TECH'!N3318=1,'RES TECH'!M3318,"*") -> RESHOUHINewOENGA20 | C3322: =IF(B3322="*","*",_xlfn.XLOOKUP(B3322,'RES TECH'!M:M,'RES TECH'!K:K)) -> RESNGA | D3322: =IF(B3322="*","*",_xlfn.XLOOKUP(B3322,'RES TECH'!M:M,'RES TECH'!L:L)) -> RESHOUHINewOEEUE | E3322: =IF(B3322="*","*",_xlfn.XLOOKUP(B3322,'RES TECH'!M:M,'RES TECH'!O:O)) -> 2020 | F3322: =IF(B3322="*","*",_xlfn.XLOOKUP(B3322,'RES TECH'!M:M,'RES TECH'!Y:Y)) -> 20 | G3322: =IF(B3322="*","*",_xlfn.XLOOKUP(B3322,'RES TECH'!M:M,'RES TECH'!V:V)) -> 1 | H3322: =IF(B3322="*","*",_xlfn.XLOOKUP(B3322,'RES TECH'!M:M,'RES TECH'!AA:AA)) -> 1 | I3322: =IF(B3322="*","*",_xlfn.XLOOKUP(B3322,'RES TECH'!M:M,'RES TECH'!Z:Z)) -> 1 | J3322: =IF(B3322="*","*",_xlfn.XLOOKUP(B3322,'RES TECH'!M:M,'RES TECH'!S:S)) -> 100 | K3322: =IF(B3322="*","*",5%*J3322) -> 5 | L3322: =IF(B3322="*","*",5%*K3322) -> 0.25 | M3322: =IF(B3322="*","*",IF(_xlfn.XLOOKUP(B3322,'RES TECH'!$M:$M,'RES TECH'!$C:$C)="Low Income",IF(G3322>1,IF(G3322>3,0.3,0.24),0.12),IF(_xlfn.XLOOKUP(B3322,'RES TECH'!$M:$M,'RES TECH'!$C:$C)="Lower-middle Income",IF(G3322>1,IF(G3322>3,0.23,0.18),0.09),IF(_xlfn.XLOOKUP(B3322,'RES TECH'!$M:$M,'RES TECH'!$C:$C)="Upper-middle Income",IF(G3322>1,IF(G3322>3,0.15,0.12),0.06),IF(_xlfn.XLOOKUP(B3322,'RES TECH'!$M:$M,'RES TECH'!$C:$C)="High Income",IF(G3322>1,IF(G3322>3,0.08,0.06),0.03)))))) -> 0.03

Sheet TECH RES _RNG
D3: ~FI_T | H3: ~FI_T
B4: TechName | C4: Comm-IN | D4: SHARE~UP | F4: TechName | G4: Comm-IN | H4: SHARE~UP~2019 | I4: SHARE~UP~2025 | J4: SHARE~UP~2100
B5: * | F5: *
B6: =IF('TECH RES'!C7="RESNGA",'TECH RES'!B7,"*") -> RESAPALOOldWH1NGA20 | C6: =IF(B6="*","*","RESNGA") -> RESNGA | D6: =IF(B6="*","*",1) -> 1 | F6: =IF('TECH RES'!C7="RESNGA",'TECH RES'!B7,"*") -> RESAPALOOldWH1NGA20 | G6: =IF(F6="*","*","RESRNG") -> RESRNG | H6: =IF(F6="*","*",0) -> 0 | I6: =IF(G6="*","*",1) -> 1 | J6: =IF(H6="*","*",1) -> 1
B7: =IF('TECH RES'!C8="RESNGA",'TECH RES'!B8,"*") -> RESAPALOOldWH2NGA20 | C7: =IF(B7="*","*","RESNGA") -> RESNGA | D7: =IF(B7="*","*",1) -> 1 | F7: =IF('TECH RES'!C8="RESNGA",'TECH RES'!B8,"*") -> RESAPALOOldWH2NGA20 | G7: =IF(F7="*","*","RESRNG") -> RESRNG | H7: =IF(F7="*","*",0) -> 0 | I7: =IF(G7="*","*",1) -> 1 | J7: =IF(H7="*","*",1) -> 1
B8: =IF('TECH RES'!C9="RESNGA",'TECH RES'!B9,"*") -> RESAPALOOldWH3NGA20 | C8: =IF(B8="*","*","RESNGA") -> RESNGA | D8: =IF(B8="*","*",1) -> 1 | F8: =IF('TECH RES'!C9="RESNGA",'TECH RES'!B9,"*") -> RESAPALOOldWH3NGA20 | G8: =IF(F8="*","*","RESRNG") -> RESRNG | H8: =IF(F8="*","*",0) -> 0 | I8: =IF(G8="*","*",1) -> 1 | J8: =IF(H8="*","*",1) -> 1
B9: =IF('TECH RES'!C10="RESNGA",'TECH RES'!B10,"*") -> RESAPALOOldWH3NGA23 | C9: =IF(B9="*","*","RESNGA") -> RESNGA | D9: =IF(B9="*","*",1) -> 1 | F9: =IF('TECH RES'!C10="RESNGA",'TECH RES'!B10,"*") -> RESAPALOOldWH3NGA23 | G9: =IF(F9="*","*","RESRNG") -> RESRNG | H9: =IF(F9="*","*",0) -> 0 | I9: =IF(G9="*","*",1) -> 1 | J9: =IF(H9="*","*",1) -> 1
B10: =IF('TECH RES'!C11="RESNGA",'TECH RES'!B11,"*") -> * | C10: =IF(B10="*","*","RESNGA") -> * | D10: =IF(B10="*","*",1) -> * | F10: =IF('TECH RES'!C11="RESNGA",'TECH RES'!B11,"*") -> * | G10: =IF(F10="*","*","RESRNG") -> * | H10: =IF(F10="*","*",0) -> * | I10: =IF(G10="*","*",1) -> * | J10: =IF(H10="*","*",1) -> *
B11: =IF('TECH RES'!C12="RESNGA",'TECH RES'!B12,"*") -> RESAPALOOldWH4NGA20 | C11: =IF(B11="*","*","RESNGA") -> RESNGA | D11: =IF(B11="*","*",1) -> 1 | F11: =IF('TECH RES'!C12="RESNGA",'TECH RES'!B12,"*") -> RESAPALOOldWH4NGA20 | G11: =IF(F11="*","*","RESRNG") -> RESRNG | H11: =IF(F11="*","*",0) -> 0 | I11: =IF(G11="*","*",1) -> 1 | J11: =IF(H11="*","*",1) -> 1
B12: =IF('TECH RES'!C13="RESNGA",'TECH RES'!B13,"*") -> RESAPALOOldWH4NGA22 | C12: =IF(B12="*","*","RESNGA") -> RESNGA | D12: =IF(B12="*","*",1) -> 1 | F12: =IF('TECH RES'!C13="RESNGA",'TECH RES'!B13,"*") -> RESAPALOOldWH4NGA22 | G12: =IF(F12="*","*","RESRNG") -> RESRNG | H12: =IF(F12="*","*",0) -> 0 | I12: =IF(G12="*","*",1) -> 1 | J12: =IF(H12="*","*",1) -> 1
B13: =IF('TECH RES'!C14="RESNGA",'TECH RES'!B14,"*") -> * | C13: =IF(B13="*","*","RESNGA") -> * | D13: =IF(B13="*","*",1) -> * | F13: =IF('TECH RES'!C14="RESNGA",'TECH RES'!B14,"*") -> * | G13: =IF(F13="*","*","RESRNG") -> * | H13: =IF(F13="*","*",0) -> * | I13: =IF(G13="*","*",1) -> * | J13: =IF(H13="*","*",1) -> *
B14: =IF('TECH RES'!C15="RESNGA",'TECH RES'!B15,"*") -> * | C14: =IF(B14="*","*","RESNGA") -> * | D14: =IF(B14="*","*",1) -> * | F14: =IF('TECH RES'!C15="RESNGA",'TECH RES'!B15,"*") -> * | G14: =IF(F14="*","*","RESRNG") -> * | H14: =IF(F14="*","*",0) -> * | I14: =IF(G14="*","*",1) -> * | J14: =IF(H14="*","*",1) -> *
B15: =IF('TECH RES'!C16="RESNGA",'TECH RES'!B16,"*") -> * | C15: =IF(B15="*","*","RESNGA") -> * | D15: =IF(B15="*","*",1) -> * | F15: =IF('TECH RES'!C16="RESNGA",'TECH RES'!B16,"*") -> * | G15: =IF(F15="*","*","RESRNG") -> * | H15: =IF(F15="*","*",0) -> * | I15: =IF(G15="*","*",1) -> * | J15: =IF(H15="*","*",1) -> *
B16: =IF('TECH RES'!C17="RESNGA",'TECH RES'!B17,"*") -> * | C16: =IF(B16="*","*","RESNGA") -> * | D16: =IF(B16="*","*",1) -> * | F16: =IF('TECH RES'!C17="RESNGA",'TECH RES'!B17,"*") -> * | G16: =IF(F16="*","*","RESRNG") -> * | H16: =IF(F16="*","*",0) -> * | I16: =IF(G16="*","*",1) -> * | J16: =IF(H16="*","*",1) -> *
B17: =IF('TECH RES'!C18="RESNGA",'TECH RES'!B18,"*") -> * | C17: =IF(B17="*","*","RESNGA") -> * | D17: =IF(B17="*","*",1) -> * | F17: =IF('TECH RES'!C18="RESNGA",'TECH RES'!B18,"*") -> * | G17: =IF(F17="*","*","RESRNG") -> * | H17: =IF(F17="*","*",0) -> * | I17: =IF(G17="*","*",1) -> * | J17: =IF(H17="*","*",1) -> *
... B3321: =IF('TECH RES'!C3322="RESNGA",'TECH RES'!B3322,"*") -> RESHOUHINewOENGA20 | C3321: =IF(B3321="*","*","RESNGA") -> RESNGA | D3321: =IF(B3321="*","*",1) -> 1 | F3321: =IF('TECH RES'!C3322="RESNGA",'TECH RES'!B3322,"*") -> RESHOUHINewOENGA20 | G3321: =IF(F3321="*","*","RESRNG") -> RESRNG | H3321: =IF(F3321="*","*",0) -> 0 | I3321: =IF(G3321="*","*",1) -> 1 | J3321: =IF(H3321="*","*",1) -> 1

Sheet >> Parameters
